{
  "Id": "37ed5d33-4859-49ea-bb33-e52648825a92",
  "DllName": "igrI18N",
  "Version": "10.0.0.603",
  "FilePath": "D:\\Off-Share\\P\u0026ID Workstation\\bin\\igri18n.dll",
  "Metadata": {
    "AssemblyName": "igrI18N",
    "Culture": null,
    "PublicKeyToken": null,
    "RuntimeVersion": "v4.0.30319",
    "ScanDate": "2026-06-07T12:43:41.669639Z"
  },
  "Dependencies": [
    {
      "AssemblyName": "mscorlib",
      "Version": "4.0.0.0",
      "IsLocalDll": false,
      "ReferencedJsonFile": null
    },
    {
      "AssemblyName": "System.Windows.Forms",
      "Version": "4.0.0.0",
      "IsLocalDll": false,
      "ReferencedJsonFile": null
    },
    {
      "AssemblyName": "System.Drawing",
      "Version": "4.0.0.0",
      "IsLocalDll": false,
      "ReferencedJsonFile": null
    },
    {
      "AssemblyName": "System.Core",
      "Version": "4.0.0.0",
      "IsLocalDll": false,
      "ReferencedJsonFile": null
    },
    {
      "AssemblyName": "PresentationFramework",
      "Version": "4.0.0.0",
      "IsLocalDll": false,
      "ReferencedJsonFile": null
    },
    {
      "AssemblyName": "System",
      "Version": "4.0.0.0",
      "IsLocalDll": false,
      "ReferencedJsonFile": null
    },
    {
      "AssemblyName": "Microsoft.CSharp",
      "Version": "4.0.0.0",
      "IsLocalDll": false,
      "ReferencedJsonFile": null
    }
  ],
  "Classes": [
    {
      "Name": "Localization",
      "Namespace": "Ingr.SP2D",
      "FullName": "Ingr.SP2D.Localization",
      "BaseType": "System.Object",
      "IsAbstract": false,
      "IsSealed": false,
      "DeclaringType": null,
      "ImplementedInterfaces": [],
      "Fields": [
        {
          "Name": "m_ErrorList",
          "Type": "System.Collections.Generic.List\u00601\u003CIngr.SP2D.ErrorStruct\u003E",
          "IsPublic": false,
          "IsStatic": false,
          "IsReadonly": true,
          "Attributes": []
        },
        {
          "Name": "m_ValidationOnly",
          "Type": "System.Boolean",
          "IsPublic": false,
          "IsStatic": false,
          "IsReadonly": false,
          "Attributes": []
        },
        {
          "Name": "m_ResourceNamespace",
          "Type": "System.String",
          "IsPublic": false,
          "IsStatic": true,
          "IsReadonly": false,
          "Attributes": []
        },
        {
          "Name": "m_ResourceItem",
          "Type": "System.Resources.ResourceManager",
          "IsPublic": false,
          "IsStatic": false,
          "IsReadonly": true,
          "Attributes": []
        },
        {
          "Name": "m_ResourceFileName",
          "Type": "System.String",
          "IsPublic": false,
          "IsStatic": false,
          "IsReadonly": false,
          "Attributes": []
        },
        {
          "Name": "m_SetAppInstanceHandle",
          "Type": "System.Int32",
          "IsPublic": false,
          "IsStatic": false,
          "IsReadonly": false,
          "Attributes": []
        },
        {
          "Name": "m_FullName",
          "Type": "System.String",
          "IsPublic": false,
          "IsStatic": false,
          "IsReadonly": false,
          "Attributes": []
        },
        {
          "Name": "m_Error",
          "Type": "System.String",
          "IsPublic": false,
          "IsStatic": false,
          "IsReadonly": true,
          "Attributes": []
        }
      ],
      "Methods": [
        {
          "Name": ".ctor",
          "ReturnType": "System.Void",
          "IsStatic": false,
          "IsPublic": true,
          "IsVirtual": false,
          "IsAbstract": false,
          "IsConstructor": true,
          "Parameters": [
            {
              "Name": "resourceFileName",
              "Type": "System.String",
              "IsOptional": false,
              "DefaultValue": null,
              "IsOut": false,
              "IsRef": false,
              "Attributes": []
            }
          ],
          "Attributes": []
        },
        {
          "Name": "DoLocalize",
          "ReturnType": "System.Void",
          "IsStatic": false,
          "IsPublic": true,
          "IsVirtual": false,
          "IsAbstract": false,
          "IsConstructor": false,
          "Parameters": [
            {
              "Name": "containerControl",
              "Type": "System.Windows.Forms.ContainerControl",
              "IsOptional": false,
              "DefaultValue": null,
              "IsOut": false,
              "IsRef": false,
              "Attributes": []
            }
          ],
          "Attributes": []
        },
        {
          "Name": "DoValidate",
          "ReturnType": "System.Collections.Generic.List\u00601\u003CIngr.SP2D.ErrorStruct\u003E",
          "IsStatic": false,
          "IsPublic": true,
          "IsVirtual": false,
          "IsAbstract": false,
          "IsConstructor": false,
          "Parameters": [
            {
              "Name": "containerControl",
              "Type": "System.Windows.Forms.ContainerControl",
              "IsOptional": false,
              "DefaultValue": null,
              "IsOut": false,
              "IsRef": false,
              "Attributes": []
            }
          ],
          "Attributes": []
        },
        {
          "Name": "GetString",
          "ReturnType": "System.String",
          "IsStatic": false,
          "IsPublic": true,
          "IsVirtual": false,
          "IsAbstract": false,
          "IsConstructor": false,
          "Parameters": [
            {
              "Name": "id",
              "Type": "System.Int32",
              "IsOptional": false,
              "DefaultValue": null,
              "IsOut": false,
              "IsRef": false,
              "Attributes": []
            }
          ],
          "Attributes": []
        },
        {
          "Name": "GetString",
          "ReturnType": "System.String",
          "IsStatic": false,
          "IsPublic": true,
          "IsVirtual": false,
          "IsAbstract": false,
          "IsConstructor": false,
          "Parameters": [
            {
              "Name": "id",
              "Type": "System.String",
              "IsOptional": false,
              "DefaultValue": null,
              "IsOut": false,
              "IsRef": false,
              "Attributes": []
            }
          ],
          "Attributes": []
        },
        {
          "Name": "GetString",
          "ReturnType": "System.String",
          "IsStatic": false,
          "IsPublic": true,
          "IsVirtual": false,
          "IsAbstract": false,
          "IsConstructor": false,
          "Parameters": [
            {
              "Name": "id",
              "Type": "System.Int32",
              "IsOptional": false,
              "DefaultValue": null,
              "IsOut": false,
              "IsRef": false,
              "Attributes": []
            },
            {
              "Name": "paramsArray",
              "Type": "System.String[]",
              "IsOptional": false,
              "DefaultValue": null,
              "IsOut": false,
              "IsRef": false,
              "Attributes": []
            }
          ],
          "Attributes": []
        },
        {
          "Name": "GetString",
          "ReturnType": "System.String",
          "IsStatic": false,
          "IsPublic": true,
          "IsVirtual": false,
          "IsAbstract": false,
          "IsConstructor": false,
          "Parameters": [
            {
              "Name": "id",
              "Type": "System.String",
              "IsOptional": false,
              "DefaultValue": null,
              "IsOut": false,
              "IsRef": false,
              "Attributes": []
            },
            {
              "Name": "paramsArray",
              "Type": "System.String[]",
              "IsOptional": false,
              "DefaultValue": null,
              "IsOut": false,
              "IsRef": false,
              "Attributes": []
            }
          ],
          "Attributes": []
        },
        {
          "Name": "GetIconByName",
          "ReturnType": "System.Drawing.Icon",
          "IsStatic": false,
          "IsPublic": true,
          "IsVirtual": false,
          "IsAbstract": false,
          "IsConstructor": false,
          "Parameters": [
            {
              "Name": "name",
              "Type": "System.String",
              "IsOptional": false,
              "DefaultValue": null,
              "IsOut": false,
              "IsRef": false,
              "Attributes": []
            }
          ],
          "Attributes": []
        },
        {
          "Name": "GetBitmapByName",
          "ReturnType": "System.Drawing.Image",
          "IsStatic": false,
          "IsPublic": true,
          "IsVirtual": false,
          "IsAbstract": false,
          "IsConstructor": false,
          "Parameters": [
            {
              "Name": "name",
              "Type": "System.String",
              "IsOptional": false,
              "DefaultValue": null,
              "IsOut": false,
              "IsRef": false,
              "Attributes": []
            }
          ],
          "Attributes": []
        },
        {
          "Name": "ShowMessageBox",
          "ReturnType": "System.Windows.Forms.DialogResult",
          "IsStatic": false,
          "IsPublic": true,
          "IsVirtual": false,
          "IsAbstract": false,
          "IsConstructor": false,
          "Parameters": [
            {
              "Name": "textID",
              "Type": "System.Int32",
              "IsOptional": false,
              "DefaultValue": null,
              "IsOut": false,
              "IsRef": false,
              "Attributes": []
            }
          ],
          "Attributes": []
        },
        {
          "Name": "ShowMessageBox",
          "ReturnType": "System.Windows.Forms.DialogResult",
          "IsStatic": false,
          "IsPublic": true,
          "IsVirtual": false,
          "IsAbstract": false,
          "IsConstructor": false,
          "Parameters": [
            {
              "Name": "owner",
              "Type": "System.Windows.Forms.IWin32Window",
              "IsOptional": false,
              "DefaultValue": null,
              "IsOut": false,
              "IsRef": false,
              "Attributes": []
            },
            {
              "Name": "textID",
              "Type": "System.Int32",
              "IsOptional": false,
              "DefaultValue": null,
              "IsOut": false,
              "IsRef": false,
              "Attributes": []
            }
          ],
          "Attributes": []
        },
        {
          "Name": "ShowMessageBox",
          "ReturnType": "System.Windows.Forms.DialogResult",
          "IsStatic": false,
          "IsPublic": true,
          "IsVirtual": false,
          "IsAbstract": false,
          "IsConstructor": false,
          "Parameters": [
            {
              "Name": "textID",
              "Type": "System.Int32",
              "IsOptional": false,
              "DefaultValue": null,
              "IsOut": false,
              "IsRef": false,
              "Attributes": []
            },
            {
              "Name": "captionID",
              "Type": "System.Int32",
              "IsOptional": false,
              "DefaultValue": null,
              "IsOut": false,
              "IsRef": false,
              "Attributes": []
            }
          ],
          "Attributes": []
        },
        {
          "Name": "ShowMessageBox",
          "ReturnType": "System.Windows.Forms.DialogResult",
          "IsStatic": false,
          "IsPublic": true,
          "IsVirtual": false,
          "IsAbstract": false,
          "IsConstructor": false,
          "Parameters": [
            {
              "Name": "owner",
              "Type": "System.Windows.Forms.IWin32Window",
              "IsOptional": false,
              "DefaultValue": null,
              "IsOut": false,
              "IsRef": false,
              "Attributes": []
            },
            {
              "Name": "textID",
              "Type": "System.Int32",
              "IsOptional": false,
              "DefaultValue": null,
              "IsOut": false,
              "IsRef": false,
              "Attributes": []
            },
            {
              "Name": "captionID",
              "Type": "System.Int32",
              "IsOptional": false,
              "DefaultValue": null,
              "IsOut": false,
              "IsRef": false,
              "Attributes": []
            }
          ],
          "Attributes": []
        },
        {
          "Name": "ShowMessageBox",
          "ReturnType": "System.Windows.Forms.DialogResult",
          "IsStatic": false,
          "IsPublic": true,
          "IsVirtual": false,
          "IsAbstract": false,
          "IsConstructor": false,
          "Parameters": [
            {
              "Name": "textID",
              "Type": "System.Int32",
              "IsOptional": false,
              "DefaultValue": null,
              "IsOut": false,
              "IsRef": false,
              "Attributes": []
            },
            {
              "Name": "captionID",
              "Type": "System.Int32",
              "IsOptional": false,
              "DefaultValue": null,
              "IsOut": false,
              "IsRef": false,
              "Attributes": []
            },
            {
              "Name": "buttons",
              "Type": "System.Windows.Forms.MessageBoxButtons",
              "IsOptional": false,
              "DefaultValue": null,
              "IsOut": false,
              "IsRef": false,
              "Attributes": []
            }
          ],
          "Attributes": []
        },
        {
          "Name": "ShowMessageBox",
          "ReturnType": "System.Windows.Forms.DialogResult",
          "IsStatic": false,
          "IsPublic": true,
          "IsVirtual": false,
          "IsAbstract": false,
          "IsConstructor": false,
          "Parameters": [
            {
              "Name": "textID",
              "Type": "System.Int32",
              "IsOptional": false,
              "DefaultValue": null,
              "IsOut": false,
              "IsRef": false,
              "Attributes": []
            },
            {
              "Name": "caption",
              "Type": "System.String",
              "IsOptional": false,
              "DefaultValue": null,
              "IsOut": false,
              "IsRef": false,
              "Attributes": []
            },
            {
              "Name": "buttons",
              "Type": "System.Windows.Forms.MessageBoxButtons",
              "IsOptional": false,
              "DefaultValue": null,
              "IsOut": false,
              "IsRef": false,
              "Attributes": []
            }
          ],
          "Attributes": []
        },
        {
          "Name": "ShowMessageBox",
          "ReturnType": "System.Windows.Forms.DialogResult",
          "IsStatic": false,
          "IsPublic": true,
          "IsVirtual": false,
          "IsAbstract": false,
          "IsConstructor": false,
          "Parameters": [
            {
              "Name": "owner",
              "Type": "System.Windows.Forms.IWin32Window",
              "IsOptional": false,
              "DefaultValue": null,
              "IsOut": false,
              "IsRef": false,
              "Attributes": []
            },
            {
              "Name": "textID",
              "Type": "System.Int32",
              "IsOptional": false,
              "DefaultValue": null,
              "IsOut": false,
              "IsRef": false,
              "Attributes": []
            },
            {
              "Name": "captionID",
              "Type": "System.Int32",
              "IsOptional": false,
              "DefaultValue": null,
              "IsOut": false,
              "IsRef": false,
              "Attributes": []
            },
            {
              "Name": "buttons",
              "Type": "System.Windows.Forms.MessageBoxButtons",
              "IsOptional": false,
              "DefaultValue": null,
              "IsOut": false,
              "IsRef": false,
              "Attributes": []
            }
          ],
          "Attributes": []
        },
        {
          "Name": "ShowMessageBox",
          "ReturnType": "System.Windows.Forms.DialogResult",
          "IsStatic": false,
          "IsPublic": true,
          "IsVirtual": false,
          "IsAbstract": false,
          "IsConstructor": false,
          "Parameters": [
            {
              "Name": "textID",
              "Type": "System.Int32",
              "IsOptional": false,
              "DefaultValue": null,
              "IsOut": false,
              "IsRef": false,
              "Attributes": []
            },
            {
              "Name": "captionID",
              "Type": "System.Int32",
              "IsOptional": false,
              "DefaultValue": null,
              "IsOut": false,
              "IsRef": false,
              "Attributes": []
            },
            {
              "Name": "buttons",
              "Type": "System.Windows.Forms.MessageBoxButtons",
              "IsOptional": false,
              "DefaultValue": null,
              "IsOut": false,
              "IsRef": false,
              "Attributes": []
            },
            {
              "Name": "icon",
              "Type": "System.Windows.Forms.MessageBoxIcon",
              "IsOptional": false,
              "DefaultValue": null,
              "IsOut": false,
              "IsRef": false,
              "Attributes": []
            }
          ],
          "Attributes": []
        },
        {
          "Name": "ShowMessageBox",
          "ReturnType": "System.Windows.Forms.DialogResult",
          "IsStatic": false,
          "IsPublic": true,
          "IsVirtual": false,
          "IsAbstract": false,
          "IsConstructor": false,
          "Parameters": [
            {
              "Name": "textID",
              "Type": "System.Int32",
              "IsOptional": false,
              "DefaultValue": null,
              "IsOut": false,
              "IsRef": false,
              "Attributes": []
            },
            {
              "Name": "caption",
              "Type": "System.String",
              "IsOptional": false,
              "DefaultValue": null,
              "IsOut": false,
              "IsRef": false,
              "Attributes": []
            },
            {
              "Name": "buttons",
              "Type": "System.Windows.Forms.MessageBoxButtons",
              "IsOptional": false,
              "DefaultValue": null,
              "IsOut": false,
              "IsRef": false,
              "Attributes": []
            },
            {
              "Name": "icon",
              "Type": "System.Windows.Forms.MessageBoxIcon",
              "IsOptional": false,
              "DefaultValue": null,
              "IsOut": false,
              "IsRef": false,
              "Attributes": []
            }
          ],
          "Attributes": []
        },
        {
          "Name": "ShowMessageBox",
          "ReturnType": "System.Windows.Forms.DialogResult",
          "IsStatic": false,
          "IsPublic": true,
          "IsVirtual": false,
          "IsAbstract": false,
          "IsConstructor": false,
          "Parameters": [
            {
              "Name": "owner",
              "Type": "System.Windows.Forms.IWin32Window",
              "IsOptional": false,
              "DefaultValue": null,
              "IsOut": false,
              "IsRef": false,
              "Attributes": []
            },
            {
              "Name": "textID",
              "Type": "System.Int32",
              "IsOptional": false,
              "DefaultValue": null,
              "IsOut": false,
              "IsRef": false,
              "Attributes": []
            },
            {
              "Name": "captionID",
              "Type": "System.Int32",
              "IsOptional": false,
              "DefaultValue": null,
              "IsOut": false,
              "IsRef": false,
              "Attributes": []
            },
            {
              "Name": "buttons",
              "Type": "System.Windows.Forms.MessageBoxButtons",
              "IsOptional": false,
              "DefaultValue": null,
              "IsOut": false,
              "IsRef": false,
              "Attributes": []
            },
            {
              "Name": "icon",
              "Type": "System.Windows.Forms.MessageBoxIcon",
              "IsOptional": false,
              "DefaultValue": null,
              "IsOut": false,
              "IsRef": false,
              "Attributes": []
            }
          ],
          "Attributes": []
        },
        {
          "Name": "ShowMessageBox",
          "ReturnType": "System.Windows.Forms.DialogResult",
          "IsStatic": false,
          "IsPublic": true,
          "IsVirtual": false,
          "IsAbstract": false,
          "IsConstructor": false,
          "Parameters": [
            {
              "Name": "textID",
              "Type": "System.Int32",
              "IsOptional": false,
              "DefaultValue": null,
              "IsOut": false,
              "IsRef": false,
              "Attributes": []
            },
            {
              "Name": "captionID",
              "Type": "System.Int32",
              "IsOptional": false,
              "DefaultValue": null,
              "IsOut": false,
              "IsRef": false,
              "Attributes": []
            },
            {
              "Name": "buttons",
              "Type": "System.Windows.Forms.MessageBoxButtons",
              "IsOptional": false,
              "DefaultValue": null,
              "IsOut": false,
              "IsRef": false,
              "Attributes": []
            },
            {
              "Name": "icon",
              "Type": "System.Windows.Forms.MessageBoxIcon",
              "IsOptional": false,
              "DefaultValue": null,
              "IsOut": false,
              "IsRef": false,
              "Attributes": []
            },
            {
              "Name": "defaultButton",
              "Type": "System.Windows.Forms.MessageBoxDefaultButton",
              "IsOptional": false,
              "DefaultValue": null,
              "IsOut": false,
              "IsRef": false,
              "Attributes": []
            }
          ],
          "Attributes": []
        },
        {
          "Name": "ShowMessageBox",
          "ReturnType": "System.Windows.Forms.DialogResult",
          "IsStatic": false,
          "IsPublic": true,
          "IsVirtual": false,
          "IsAbstract": false,
          "IsConstructor": false,
          "Parameters": [
            {
              "Name": "owner",
              "Type": "System.Windows.Forms.IWin32Window",
              "IsOptional": false,
              "DefaultValue": null,
              "IsOut": false,
              "IsRef": false,
              "Attributes": []
            },
            {
              "Name": "textID",
              "Type": "System.Int32",
              "IsOptional": false,
              "DefaultValue": null,
              "IsOut": false,
              "IsRef": false,
              "Attributes": []
            },
            {
              "Name": "captionID",
              "Type": "System.Int32",
              "IsOptional": false,
              "DefaultValue": null,
              "IsOut": false,
              "IsRef": false,
              "Attributes": []
            },
            {
              "Name": "buttons",
              "Type": "System.Windows.Forms.MessageBoxButtons",
              "IsOptional": false,
              "DefaultValue": null,
              "IsOut": false,
              "IsRef": false,
              "Attributes": []
            },
            {
              "Name": "icon",
              "Type": "System.Windows.Forms.MessageBoxIcon",
              "IsOptional": false,
              "DefaultValue": null,
              "IsOut": false,
              "IsRef": false,
              "Attributes": []
            },
            {
              "Name": "defaultButton",
              "Type": "System.Windows.Forms.MessageBoxDefaultButton",
              "IsOptional": false,
              "DefaultValue": null,
              "IsOut": false,
              "IsRef": false,
              "Attributes": []
            }
          ],
          "Attributes": []
        },
        {
          "Name": "ShowMessageBox",
          "ReturnType": "System.Windows.Forms.DialogResult",
          "IsStatic": false,
          "IsPublic": true,
          "IsVirtual": false,
          "IsAbstract": false,
          "IsConstructor": false,
          "Parameters": [
            {
              "Name": "textID",
              "Type": "System.Int32",
              "IsOptional": false,
              "DefaultValue": null,
              "IsOut": false,
              "IsRef": false,
              "Attributes": []
            },
            {
              "Name": "captionID",
              "Type": "System.Int32",
              "IsOptional": false,
              "DefaultValue": null,
              "IsOut": false,
              "IsRef": false,
              "Attributes": []
            },
            {
              "Name": "buttons",
              "Type": "System.Windows.Forms.MessageBoxButtons",
              "IsOptional": false,
              "DefaultValue": null,
              "IsOut": false,
              "IsRef": false,
              "Attributes": []
            },
            {
              "Name": "icon",
              "Type": "System.Windows.Forms.MessageBoxIcon",
              "IsOptional": false,
              "DefaultValue": null,
              "IsOut": false,
              "IsRef": false,
              "Attributes": []
            },
            {
              "Name": "defaultButton",
              "Type": "System.Windows.Forms.MessageBoxDefaultButton",
              "IsOptional": false,
              "DefaultValue": null,
              "IsOut": false,
              "IsRef": false,
              "Attributes": []
            },
            {
              "Name": "options",
              "Type": "System.Windows.Forms.MessageBoxOptions",
              "IsOptional": false,
              "DefaultValue": null,
              "IsOut": false,
              "IsRef": false,
              "Attributes": []
            }
          ],
          "Attributes": []
        },
        {
          "Name": "ShowMessageBox",
          "ReturnType": "System.Windows.Forms.DialogResult",
          "IsStatic": false,
          "IsPublic": true,
          "IsVirtual": false,
          "IsAbstract": false,
          "IsConstructor": false,
          "Parameters": [
            {
              "Name": "owner",
              "Type": "System.Windows.Forms.IWin32Window",
              "IsOptional": false,
              "DefaultValue": null,
              "IsOut": false,
              "IsRef": false,
              "Attributes": []
            },
            {
              "Name": "textID",
              "Type": "System.Int32",
              "IsOptional": false,
              "DefaultValue": null,
              "IsOut": false,
              "IsRef": false,
              "Attributes": []
            },
            {
              "Name": "captionID",
              "Type": "System.Int32",
              "IsOptional": false,
              "DefaultValue": null,
              "IsOut": false,
              "IsRef": false,
              "Attributes": []
            },
            {
              "Name": "buttons",
              "Type": "System.Windows.Forms.MessageBoxButtons",
              "IsOptional": false,
              "DefaultValue": null,
              "IsOut": false,
              "IsRef": false,
              "Attributes": []
            },
            {
              "Name": "icon",
              "Type": "System.Windows.Forms.MessageBoxIcon",
              "IsOptional": false,
              "DefaultValue": null,
              "IsOut": false,
              "IsRef": false,
              "Attributes": []
            },
            {
              "Name": "defaultButton",
              "Type": "System.Windows.Forms.MessageBoxDefaultButton",
              "IsOptional": false,
              "DefaultValue": null,
              "IsOut": false,
              "IsRef": false,
              "Attributes": []
            },
            {
              "Name": "options",
              "Type": "System.Windows.Forms.MessageBoxOptions",
              "IsOptional": false,
              "DefaultValue": null,
              "IsOut": false,
              "IsRef": false,
              "Attributes": []
            }
          ],
          "Attributes": []
        },
        {
          "Name": "ShowMessageBox",
          "ReturnType": "System.Windows.Forms.DialogResult",
          "IsStatic": false,
          "IsPublic": true,
          "IsVirtual": false,
          "IsAbstract": false,
          "IsConstructor": false,
          "Parameters": [
            {
              "Name": "textID",
              "Type": "System.Int32",
              "IsOptional": false,
              "DefaultValue": null,
              "IsOut": false,
              "IsRef": false,
              "Attributes": []
            },
            {
              "Name": "captionID",
              "Type": "System.Int32",
              "IsOptional": false,
              "DefaultValue": null,
              "IsOut": false,
              "IsRef": false,
              "Attributes": []
            },
            {
              "Name": "buttons",
              "Type": "System.Windows.Forms.MessageBoxButtons",
              "IsOptional": false,
              "DefaultValue": null,
              "IsOut": false,
              "IsRef": false,
              "Attributes": []
            },
            {
              "Name": "icon",
              "Type": "System.Windows.Forms.MessageBoxIcon",
              "IsOptional": false,
              "DefaultValue": null,
              "IsOut": false,
              "IsRef": false,
              "Attributes": []
            },
            {
              "Name": "defaultButton",
              "Type": "System.Windows.Forms.MessageBoxDefaultButton",
              "IsOptional": false,
              "DefaultValue": null,
              "IsOut": false,
              "IsRef": false,
              "Attributes": []
            },
            {
              "Name": "options",
              "Type": "System.Windows.Forms.MessageBoxOptions",
              "IsOptional": false,
              "DefaultValue": null,
              "IsOut": false,
              "IsRef": false,
              "Attributes": []
            },
            {
              "Name": "displayHelpButton",
              "Type": "System.Boolean",
              "IsOptional": false,
              "DefaultValue": null,
              "IsOut": false,
              "IsRef": false,
              "Attributes": []
            }
          ],
          "Attributes": []
        },
        {
          "Name": "ShowMessageBox",
          "ReturnType": "System.Windows.Forms.DialogResult",
          "IsStatic": false,
          "IsPublic": true,
          "IsVirtual": false,
          "IsAbstract": false,
          "IsConstructor": false,
          "Parameters": [
            {
              "Name": "textID",
              "Type": "System.Int32",
              "IsOptional": false,
              "DefaultValue": null,
              "IsOut": false,
              "IsRef": false,
              "Attributes": []
            },
            {
              "Name": "captionID",
              "Type": "System.Int32",
              "IsOptional": false,
              "DefaultValue": null,
              "IsOut": false,
              "IsRef": false,
              "Attributes": []
            },
            {
              "Name": "buttons",
              "Type": "System.Windows.Forms.MessageBoxButtons",
              "IsOptional": false,
              "DefaultValue": null,
              "IsOut": false,
              "IsRef": false,
              "Attributes": []
            },
            {
              "Name": "icon",
              "Type": "System.Windows.Forms.MessageBoxIcon",
              "IsOptional": false,
              "DefaultValue": null,
              "IsOut": false,
              "IsRef": false,
              "Attributes": []
            },
            {
              "Name": "defaultButton",
              "Type": "System.Windows.Forms.MessageBoxDefaultButton",
              "IsOptional": false,
              "DefaultValue": null,
              "IsOut": false,
              "IsRef": false,
              "Attributes": []
            },
            {
              "Name": "options",
              "Type": "System.Windows.Forms.MessageBoxOptions",
              "IsOptional": false,
              "DefaultValue": null,
              "IsOut": false,
              "IsRef": false,
              "Attributes": []
            },
            {
              "Name": "helpFilePath",
              "Type": "System.String",
              "IsOptional": false,
              "DefaultValue": null,
              "IsOut": false,
              "IsRef": false,
              "Attributes": []
            }
          ],
          "Attributes": []
        },
        {
          "Name": "ShowMessageBox",
          "ReturnType": "System.Windows.Forms.DialogResult",
          "IsStatic": false,
          "IsPublic": true,
          "IsVirtual": false,
          "IsAbstract": false,
          "IsConstructor": false,
          "Parameters": [
            {
              "Name": "owner",
              "Type": "System.Windows.Forms.IWin32Window",
              "IsOptional": false,
              "DefaultValue": null,
              "IsOut": false,
              "IsRef": false,
              "Attributes": []
            },
            {
              "Name": "textID",
              "Type": "System.Int32",
              "IsOptional": false,
              "DefaultValue": null,
              "IsOut": false,
              "IsRef": false,
              "Attributes": []
            },
            {
              "Name": "captionID",
              "Type": "System.Int32",
              "IsOptional": false,
              "DefaultValue": null,
              "IsOut": false,
              "IsRef": false,
              "Attributes": []
            },
            {
              "Name": "buttons",
              "Type": "System.Windows.Forms.MessageBoxButtons",
              "IsOptional": false,
              "DefaultValue": null,
              "IsOut": false,
              "IsRef": false,
              "Attributes": []
            },
            {
              "Name": "icon",
              "Type": "System.Windows.Forms.MessageBoxIcon",
              "IsOptional": false,
              "DefaultValue": null,
              "IsOut": false,
              "IsRef": false,
              "Attributes": []
            },
            {
              "Name": "defaultButton",
              "Type": "System.Windows.Forms.MessageBoxDefaultButton",
              "IsOptional": false,
              "DefaultValue": null,
              "IsOut": false,
              "IsRef": false,
              "Attributes": []
            },
            {
              "Name": "options",
              "Type": "System.Windows.Forms.MessageBoxOptions",
              "IsOptional": false,
              "DefaultValue": null,
              "IsOut": false,
              "IsRef": false,
              "Attributes": []
            },
            {
              "Name": "helpFilePath",
              "Type": "System.String",
              "IsOptional": false,
              "DefaultValue": null,
              "IsOut": false,
              "IsRef": false,
              "Attributes": []
            }
          ],
          "Attributes": []
        },
        {
          "Name": "ShowMessageBox",
          "ReturnType": "System.Windows.Forms.DialogResult",
          "IsStatic": false,
          "IsPublic": true,
          "IsVirtual": false,
          "IsAbstract": false,
          "IsConstructor": false,
          "Parameters": [
            {
              "Name": "textID",
              "Type": "System.Int32",
              "IsOptional": false,
              "DefaultValue": null,
              "IsOut": false,
              "IsRef": false,
              "Attributes": []
            },
            {
              "Name": "captionID",
              "Type": "System.Int32",
              "IsOptional": false,
              "DefaultValue": null,
              "IsOut": false,
              "IsRef": false,
              "Attributes": []
            },
            {
              "Name": "buttons",
              "Type": "System.Windows.Forms.MessageBoxButtons",
              "IsOptional": false,
              "DefaultValue": null,
              "IsOut": false,
              "IsRef": false,
              "Attributes": []
            },
            {
              "Name": "icon",
              "Type": "System.Windows.Forms.MessageBoxIcon",
              "IsOptional": false,
              "DefaultValue": null,
              "IsOut": false,
              "IsRef": false,
              "Attributes": []
            },
            {
              "Name": "defaultButton",
              "Type": "System.Windows.Forms.MessageBoxDefaultButton",
              "IsOptional": false,
              "DefaultValue": null,
              "IsOut": false,
              "IsRef": false,
              "Attributes": []
            },
            {
              "Name": "options",
              "Type": "System.Windows.Forms.MessageBoxOptions",
              "IsOptional": false,
              "DefaultValue": null,
              "IsOut": false,
              "IsRef": false,
              "Attributes": []
            },
            {
              "Name": "helpFilePath",
              "Type": "System.String",
              "IsOptional": false,
              "DefaultValue": null,
              "IsOut": false,
              "IsRef": false,
              "Attributes": []
            },
            {
              "Name": "navigator",
              "Type": "System.Windows.Forms.HelpNavigator",
              "IsOptional": false,
              "DefaultValue": null,
              "IsOut": false,
              "IsRef": false,
              "Attributes": []
            }
          ],
          "Attributes": []
        },
        {
          "Name": "ShowMessageBox",
          "ReturnType": "System.Windows.Forms.DialogResult",
          "IsStatic": false,
          "IsPublic": true,
          "IsVirtual": false,
          "IsAbstract": false,
          "IsConstructor": false,
          "Parameters": [
            {
              "Name": "textID",
              "Type": "System.Int32",
              "IsOptional": false,
              "DefaultValue": null,
              "IsOut": false,
              "IsRef": false,
              "Attributes": []
            },
            {
              "Name": "captionID",
              "Type": "System.Int32",
              "IsOptional": false,
              "DefaultValue": null,
              "IsOut": false,
              "IsRef": false,
              "Attributes": []
            },
            {
              "Name": "buttons",
              "Type": "System.Windows.Forms.MessageBoxButtons",
              "IsOptional": false,
              "DefaultValue": null,
              "IsOut": false,
              "IsRef": false,
              "Attributes": []
            },
            {
              "Name": "icon",
              "Type": "System.Windows.Forms.MessageBoxIcon",
              "IsOptional": false,
              "DefaultValue": null,
              "IsOut": false,
              "IsRef": false,
              "Attributes": []
            },
            {
              "Name": "defaultButton",
              "Type": "System.Windows.Forms.MessageBoxDefaultButton",
              "IsOptional": false,
              "DefaultValue": null,
              "IsOut": false,
              "IsRef": false,
              "Attributes": []
            },
            {
              "Name": "options",
              "Type": "System.Windows.Forms.MessageBoxOptions",
              "IsOptional": false,
              "DefaultValue": null,
              "IsOut": false,
              "IsRef": false,
              "Attributes": []
            },
            {
              "Name": "helpFilePath",
              "Type": "System.String",
              "IsOptional": false,
              "DefaultValue": null,
              "IsOut": false,
              "IsRef": false,
              "Attributes": []
            },
            {
              "Name": "keyword",
              "Type": "System.String",
              "IsOptional": false,
              "DefaultValue": null,
              "IsOut": false,
              "IsRef": false,
              "Attributes": []
            }
          ],
          "Attributes": []
        },
        {
          "Name": "ShowMessageBox",
          "ReturnType": "System.Windows.Forms.DialogResult",
          "IsStatic": false,
          "IsPublic": true,
          "IsVirtual": false,
          "IsAbstract": false,
          "IsConstructor": false,
          "Parameters": [
            {
              "Name": "textID",
              "Type": "System.Int32",
              "IsOptional": false,
              "DefaultValue": null,
              "IsOut": false,
              "IsRef": false,
              "Attributes": []
            },
            {
              "Name": "caption",
              "Type": "System.String",
              "IsOptional": false,
              "DefaultValue": null,
              "IsOut": false,
              "IsRef": false,
              "Attributes": []
            },
            {
              "Name": "buttons",
              "Type": "System.Windows.Forms.MessageBoxButtons",
              "IsOptional": false,
              "DefaultValue": null,
              "IsOut": false,
              "IsRef": false,
              "Attributes": []
            },
            {
              "Name": "icon",
              "Type": "System.Windows.Forms.MessageBoxIcon",
              "IsOptional": false,
              "DefaultValue": null,
              "IsOut": false,
              "IsRef": false,
              "Attributes": []
            },
            {
              "Name": "defaultButton",
              "Type": "System.Windows.Forms.MessageBoxDefaultButton",
              "IsOptional": false,
              "DefaultValue": null,
              "IsOut": false,
              "IsRef": false,
              "Attributes": []
            },
            {
              "Name": "options",
              "Type": "System.Windows.Forms.MessageBoxOptions",
              "IsOptional": false,
              "DefaultValue": null,
              "IsOut": false,
              "IsRef": false,
              "Attributes": []
            },
            {
              "Name": "helpFilePath",
              "Type": "System.String",
              "IsOptional": false,
              "DefaultValue": null,
              "IsOut": false,
              "IsRef": false,
              "Attributes": []
            },
            {
              "Name": "keyword",
              "Type": "System.String",
              "IsOptional": false,
              "DefaultValue": null,
              "IsOut": false,
              "IsRef": false,
              "Attributes": []
            }
          ],
          "Attributes": []
        },
        {
          "Name": "ShowMessageBox",
          "ReturnType": "System.Windows.Forms.DialogResult",
          "IsStatic": false,
          "IsPublic": true,
          "IsVirtual": false,
          "IsAbstract": false,
          "IsConstructor": false,
          "Parameters": [
            {
              "Name": "owner",
              "Type": "System.Windows.Forms.IWin32Window",
              "IsOptional": false,
              "DefaultValue": null,
              "IsOut": false,
              "IsRef": false,
              "Attributes": []
            },
            {
              "Name": "textID",
              "Type": "System.Int32",
              "IsOptional": false,
              "DefaultValue": null,
              "IsOut": false,
              "IsRef": false,
              "Attributes": []
            },
            {
              "Name": "captionID",
              "Type": "System.Int32",
              "IsOptional": false,
              "DefaultValue": null,
              "IsOut": false,
              "IsRef": false,
              "Attributes": []
            },
            {
              "Name": "buttons",
              "Type": "System.Windows.Forms.MessageBoxButtons",
              "IsOptional": false,
              "DefaultValue": null,
              "IsOut": false,
              "IsRef": false,
              "Attributes": []
            },
            {
              "Name": "icon",
              "Type": "System.Windows.Forms.MessageBoxIcon",
              "IsOptional": false,
              "DefaultValue": null,
              "IsOut": false,
              "IsRef": false,
              "Attributes": []
            },
            {
              "Name": "defaultButton",
              "Type": "System.Windows.Forms.MessageBoxDefaultButton",
              "IsOptional": false,
              "DefaultValue": null,
              "IsOut": false,
              "IsRef": false,
              "Attributes": []
            },
            {
              "Name": "options",
              "Type": "System.Windows.Forms.MessageBoxOptions",
              "IsOptional": false,
              "DefaultValue": null,
              "IsOut": false,
              "IsRef": false,
              "Attributes": []
            },
            {
              "Name": "helpFilePath",
              "Type": "System.String",
              "IsOptional": false,
              "DefaultValue": null,
              "IsOut": false,
              "IsRef": false,
              "Attributes": []
            },
            {
              "Name": "navigator",
              "Type": "System.Windows.Forms.HelpNavigator",
              "IsOptional": false,
              "DefaultValue": null,
              "IsOut": false,
              "IsRef": false,
              "Attributes": []
            }
          ],
          "Attributes": []
        },
        {
          "Name": "ShowMessageBox",
          "ReturnType": "System.Windows.Forms.DialogResult",
          "IsStatic": false,
          "IsPublic": true,
          "IsVirtual": false,
          "IsAbstract": false,
          "IsConstructor": false,
          "Parameters": [
            {
              "Name": "owner",
              "Type": "System.Windows.Forms.IWin32Window",
              "IsOptional": false,
              "DefaultValue": null,
              "IsOut": false,
              "IsRef": false,
              "Attributes": []
            },
            {
              "Name": "textID",
              "Type": "System.Int32",
              "IsOptional": false,
              "DefaultValue": null,
              "IsOut": false,
              "IsRef": false,
              "Attributes": []
            },
            {
              "Name": "captionID",
              "Type": "System.Int32",
              "IsOptional": false,
              "DefaultValue": null,
              "IsOut": false,
              "IsRef": false,
              "Attributes": []
            },
            {
              "Name": "buttons",
              "Type": "System.Windows.Forms.MessageBoxButtons",
              "IsOptional": false,
              "DefaultValue": null,
              "IsOut": false,
              "IsRef": false,
              "Attributes": []
            },
            {
              "Name": "icon",
              "Type": "System.Windows.Forms.MessageBoxIcon",
              "IsOptional": false,
              "DefaultValue": null,
              "IsOut": false,
              "IsRef": false,
              "Attributes": []
            },
            {
              "Name": "defaultButton",
              "Type": "System.Windows.Forms.MessageBoxDefaultButton",
              "IsOptional": false,
              "DefaultValue": null,
              "IsOut": false,
              "IsRef": false,
              "Attributes": []
            },
            {
              "Name": "options",
              "Type": "System.Windows.Forms.MessageBoxOptions",
              "IsOptional": false,
              "DefaultValue": null,
              "IsOut": false,
              "IsRef": false,
              "Attributes": []
            },
            {
              "Name": "helpFilePath",
              "Type": "System.String",
              "IsOptional": false,
              "DefaultValue": null,
              "IsOut": false,
              "IsRef": false,
              "Attributes": []
            },
            {
              "Name": "keyword",
              "Type": "System.String",
              "IsOptional": false,
              "DefaultValue": null,
              "IsOut": false,
              "IsRef": false,
              "Attributes": []
            }
          ],
          "Attributes": []
        },
        {
          "Name": "ShowMessageBox",
          "ReturnType": "System.Windows.Forms.DialogResult",
          "IsStatic": false,
          "IsPublic": true,
          "IsVirtual": false,
          "IsAbstract": false,
          "IsConstructor": false,
          "Parameters": [
            {
              "Name": "textID",
              "Type": "System.Int32",
              "IsOptional": false,
              "DefaultValue": null,
              "IsOut": false,
              "IsRef": false,
              "Attributes": []
            },
            {
              "Name": "captionID",
              "Type": "System.Int32",
              "IsOptional": false,
              "DefaultValue": null,
              "IsOut": false,
              "IsRef": false,
              "Attributes": []
            },
            {
              "Name": "buttons",
              "Type": "System.Windows.Forms.MessageBoxButtons",
              "IsOptional": false,
              "DefaultValue": null,
              "IsOut": false,
              "IsRef": false,
              "Attributes": []
            },
            {
              "Name": "icon",
              "Type": "System.Windows.Forms.MessageBoxIcon",
              "IsOptional": false,
              "DefaultValue": null,
              "IsOut": false,
              "IsRef": false,
              "Attributes": []
            },
            {
              "Name": "defaultButton",
              "Type": "System.Windows.Forms.MessageBoxDefaultButton",
              "IsOptional": false,
              "DefaultValue": null,
              "IsOut": false,
              "IsRef": false,
              "Attributes": []
            },
            {
              "Name": "options",
              "Type": "System.Windows.Forms.MessageBoxOptions",
              "IsOptional": false,
              "DefaultValue": null,
              "IsOut": false,
              "IsRef": false,
              "Attributes": []
            },
            {
              "Name": "helpFilePath",
              "Type": "System.String",
              "IsOptional": false,
              "DefaultValue": null,
              "IsOut": false,
              "IsRef": false,
              "Attributes": []
            },
            {
              "Name": "navigator",
              "Type": "System.Windows.Forms.HelpNavigator",
              "IsOptional": false,
              "DefaultValue": null,
              "IsOut": false,
              "IsRef": false,
              "Attributes": []
            },
            {
              "Name": "param",
              "Type": "System.Object",
              "IsOptional": false,
              "DefaultValue": null,
              "IsOut": false,
              "IsRef": false,
              "Attributes": []
            }
          ],
          "Attributes": []
        },
        {
          "Name": "ShowMessageBox",
          "ReturnType": "System.Windows.Forms.DialogResult",
          "IsStatic": false,
          "IsPublic": true,
          "IsVirtual": false,
          "IsAbstract": false,
          "IsConstructor": false,
          "Parameters": [
            {
              "Name": "owner",
              "Type": "System.Windows.Forms.IWin32Window",
              "IsOptional": false,
              "DefaultValue": null,
              "IsOut": false,
              "IsRef": false,
              "Attributes": []
            },
            {
              "Name": "textID",
              "Type": "System.Int32",
              "IsOptional": false,
              "DefaultValue": null,
              "IsOut": false,
              "IsRef": false,
              "Attributes": []
            },
            {
              "Name": "captionID",
              "Type": "System.Int32",
              "IsOptional": false,
              "DefaultValue": null,
              "IsOut": false,
              "IsRef": false,
              "Attributes": []
            },
            {
              "Name": "buttons",
              "Type": "System.Windows.Forms.MessageBoxButtons",
              "IsOptional": false,
              "DefaultValue": null,
              "IsOut": false,
              "IsRef": false,
              "Attributes": []
            },
            {
              "Name": "icon",
              "Type": "System.Windows.Forms.MessageBoxIcon",
              "IsOptional": false,
              "DefaultValue": null,
              "IsOut": false,
              "IsRef": false,
              "Attributes": []
            },
            {
              "Name": "defaultButton",
              "Type": "System.Windows.Forms.MessageBoxDefaultButton",
              "IsOptional": false,
              "DefaultValue": null,
              "IsOut": false,
              "IsRef": false,
              "Attributes": []
            },
            {
              "Name": "options",
              "Type": "System.Windows.Forms.MessageBoxOptions",
              "IsOptional": false,
              "DefaultValue": null,
              "IsOut": false,
              "IsRef": false,
              "Attributes": []
            },
            {
              "Name": "helpFilePath",
              "Type": "System.String",
              "IsOptional": false,
              "DefaultValue": null,
              "IsOut": false,
              "IsRef": false,
              "Attributes": []
            },
            {
              "Name": "navigator",
              "Type": "System.Windows.Forms.HelpNavigator",
              "IsOptional": false,
              "DefaultValue": null,
              "IsOut": false,
              "IsRef": false,
              "Attributes": []
            },
            {
              "Name": "param",
              "Type": "System.Object",
              "IsOptional": false,
              "DefaultValue": null,
              "IsOut": false,
              "IsRef": false,
              "Attributes": []
            }
          ],
          "Attributes": []
        },
        {
          "Name": "AddError",
          "ReturnType": "System.Void",
          "IsStatic": false,
          "IsPublic": false,
          "IsVirtual": false,
          "IsAbstract": false,
          "IsConstructor": false,
          "Parameters": [
            {
              "Name": "containerName",
              "Type": "System.String",
              "IsOptional": false,
              "DefaultValue": null,
              "IsOut": false,
              "IsRef": false,
              "Attributes": []
            },
            {
              "Name": "controlName",
              "Type": "System.String",
              "IsOptional": false,
              "DefaultValue": null,
              "IsOut": false,
              "IsRef": false,
              "Attributes": []
            },
            {
              "Name": "errorDescription",
              "Type": "System.String",
              "IsOptional": false,
              "DefaultValue": null,
              "IsOut": false,
              "IsRef": false,
              "Attributes": []
            }
          ],
          "Attributes": []
        },
        {
          "Name": "LocalizationHandler",
          "ReturnType": "System.Void",
          "IsStatic": false,
          "IsPublic": false,
          "IsVirtual": false,
          "IsAbstract": false,
          "IsConstructor": false,
          "Parameters": [
            {
              "Name": "toLocalize",
              "Type": "System.Boolean",
              "IsOptional": false,
              "DefaultValue": null,
              "IsOut": false,
              "IsRef": false,
              "Attributes": []
            },
            {
              "Name": "container",
              "Type": "System.Windows.Forms.ContainerControl",
              "IsOptional": false,
              "DefaultValue": null,
              "IsOut": false,
              "IsRef": false,
              "Attributes": []
            }
          ],
          "Attributes": []
        },
        {
          "Name": "Localize",
          "ReturnType": "System.Void",
          "IsStatic": false,
          "IsPublic": false,
          "IsVirtual": false,
          "IsAbstract": false,
          "IsConstructor": false,
          "Parameters": [
            {
              "Name": "currentControl",
              "Type": "System.Object",
              "IsOptional": false,
              "DefaultValue": null,
              "IsOut": false,
              "IsRef": false,
              "Attributes": []
            },
            {
              "Name": "containerName",
              "Type": "System.String",
              "IsOptional": false,
              "DefaultValue": null,
              "IsOut": false,
              "IsRef": false,
              "Attributes": []
            },
            {
              "Name": "toLocalize",
              "Type": "System.Boolean",
              "IsOptional": false,
              "DefaultValue": null,
              "IsOut": false,
              "IsRef": false,
              "Attributes": []
            },
            {
              "Name": "typeOfWindow",
              "Type": "Ingr.SP2D.WinType",
              "IsOptional": false,
              "DefaultValue": null,
              "IsOut": false,
              "IsRef": false,
              "Attributes": []
            }
          ],
          "Attributes": []
        },
        {
          "Name": "tagHandler",
          "ReturnType": "System.Boolean",
          "IsStatic": false,
          "IsPublic": false,
          "IsVirtual": false,
          "IsAbstract": false,
          "IsConstructor": false,
          "Parameters": [
            {
              "Name": "containerControlName",
              "Type": "System.String",
              "IsOptional": false,
              "DefaultValue": null,
              "IsOut": false,
              "IsRef": false,
              "Attributes": []
            },
            {
              "Name": "controlName",
              "Type": "System.String",
              "IsOptional": false,
              "DefaultValue": null,
              "IsOut": false,
              "IsRef": false,
              "Attributes": []
            },
            {
              "Name": "stringID",
              "Type": "System.String",
              "IsOptional": false,
              "DefaultValue": null,
              "IsOut": false,
              "IsRef": false,
              "Attributes": []
            }
          ],
          "Attributes": []
        },
        {
          "Name": "GetToolStripItems",
          "ReturnType": "System.Void",
          "IsStatic": false,
          "IsPublic": false,
          "IsVirtual": false,
          "IsAbstract": false,
          "IsConstructor": false,
          "Parameters": [
            {
              "Name": "item",
              "Type": "System.Windows.Forms.ToolStripItem",
              "IsOptional": false,
              "DefaultValue": null,
              "IsOut": false,
              "IsRef": false,
              "Attributes": []
            },
            {
              "Name": "items",
              "Type": "System.Collections.Generic.List\u00601\u003CSystem.Windows.Forms.ToolStripItem\u003E",
              "IsOptional": false,
              "DefaultValue": null,
              "IsOut": false,
              "IsRef": false,
              "Attributes": []
            }
          ],
          "Attributes": []
        },
        {
          "Name": "CollectControlsRecursive",
          "ReturnType": "System.Void",
          "IsStatic": false,
          "IsPublic": false,
          "IsVirtual": false,
          "IsAbstract": false,
          "IsConstructor": false,
          "Parameters": [
            {
              "Name": "a",
              "Type": "System.Windows.Forms.Control",
              "IsOptional": false,
              "DefaultValue": null,
              "IsOut": false,
              "IsRef": false,
              "Attributes": []
            },
            {
              "Name": "controlArray",
              "Type": "System.Collections.Generic.IList\u00601\u003CSystem.Windows.Forms.Control\u003E",
              "IsOptional": false,
              "DefaultValue": null,
              "IsOut": false,
              "IsRef": false,
              "Attributes": []
            }
          ],
          "Attributes": []
        },
        {
          "Name": "GetStringInternal",
          "ReturnType": "System.String",
          "IsStatic": false,
          "IsPublic": false,
          "IsVirtual": false,
          "IsAbstract": false,
          "IsConstructor": false,
          "Parameters": [
            {
              "Name": "id",
              "Type": "System.String",
              "IsOptional": false,
              "DefaultValue": null,
              "IsOut": false,
              "IsRef": false,
              "Attributes": []
            }
          ],
          "Attributes": []
        },
        {
          "Name": "DoLocalizeWPF",
          "ReturnType": "System.Collections.Generic.List\u00601\u003CIngr.SP2D.ErrorStruct\u003E",
          "IsStatic": false,
          "IsPublic": true,
          "IsVirtual": false,
          "IsAbstract": false,
          "IsConstructor": false,
          "Parameters": [
            {
              "Name": "containerControl",
              "Type": "System.Windows.Controls.ContentControl",
              "IsOptional": false,
              "DefaultValue": null,
              "IsOut": false,
              "IsRef": false,
              "Attributes": []
            }
          ],
          "Attributes": []
        },
        {
          "Name": "DoValidateWPF",
          "ReturnType": "System.Collections.Generic.List\u00601\u003CIngr.SP2D.ErrorStruct\u003E",
          "IsStatic": false,
          "IsPublic": true,
          "IsVirtual": false,
          "IsAbstract": false,
          "IsConstructor": false,
          "Parameters": [
            {
              "Name": "containerControl",
              "Type": "System.Windows.Controls.ContentControl",
              "IsOptional": false,
              "DefaultValue": null,
              "IsOut": false,
              "IsRef": false,
              "Attributes": []
            }
          ],
          "Attributes": []
        },
        {
          "Name": "CollectWPFControlsRecursive",
          "ReturnType": "System.Void",
          "IsStatic": false,
          "IsPublic": false,
          "IsVirtual": false,
          "IsAbstract": false,
          "IsConstructor": false,
          "Parameters": [
            {
              "Name": "a",
              "Type": "System.Windows.Controls.Control",
              "IsOptional": false,
              "DefaultValue": null,
              "IsOut": false,
              "IsRef": false,
              "Attributes": []
            },
            {
              "Name": "controlArray",
              "Type": "System.Collections.Generic.List\u00601\u003CSystem.Windows.Controls.Control\u003E",
              "IsOptional": false,
              "DefaultValue": null,
              "IsOut": false,
              "IsRef": false,
              "Attributes": []
            }
          ],
          "Attributes": []
        },
        {
          "Name": "LocalizationHandler",
          "ReturnType": "System.Void",
          "IsStatic": false,
          "IsPublic": false,
          "IsVirtual": false,
          "IsAbstract": false,
          "IsConstructor": false,
          "Parameters": [
            {
              "Name": "toLocalize",
              "Type": "System.Boolean",
              "IsOptional": false,
              "DefaultValue": null,
              "IsOut": false,
              "IsRef": false,
              "Attributes": []
            },
            {
              "Name": "container",
              "Type": "System.Windows.Controls.ContentControl",
              "IsOptional": false,
              "DefaultValue": null,
              "IsOut": false,
              "IsRef": false,
              "Attributes": []
            }
          ],
          "Attributes": []
        }
      ],
      "Properties": [
        {
          "Name": "ResourceItem",
          "Type": "System.Resources.ResourceManager",
          "CanRead": true,
          "CanWrite": false
        },
        {
          "Name": "AppPath",
          "Type": "System.String",
          "CanRead": true,
          "CanWrite": true
        },
        {
          "Name": "FullName",
          "Type": "System.String",
          "CanRead": true,
          "CanWrite": false
        },
        {
          "Name": "SetAppInstanceHandle",
          "Type": "System.Int32",
          "CanRead": false,
          "CanWrite": true
        },
        {
          "Name": "Error",
          "Type": "System.String",
          "CanRead": true,
          "CanWrite": false
        }
      ],
      "Events": [],
      "Attributes": []
    }
  ],
  "Interfaces": [],
  "Structs": [
    {
      "Name": "ErrorStruct",
      "Namespace": "Ingr.SP2D",
      "FullName": "Ingr.SP2D.ErrorStruct",
      "DeclaringType": null,
      "Properties": []
    }
  ],
  "Enums": [
    {
      "Name": "WinType",
      "Namespace": "Ingr.SP2D",
      "FullName": "Ingr.SP2D.WinType",
      "DeclaringType": null,
      "Values": [
        "WinForm",
        "WPF"
      ]
    }
  ],
  "Delegates": []
}