{
  "Id": "e0f75677-f85b-4be5-b8bd-6120d9c1627d",
  "DllName": "igrORASPConnect420",
  "Version": "10.0.0.603",
  "FilePath": "D:\\Off-Share\\P\u0026ID Workstation\\bin\\igroraspconnect420.dll",
  "Metadata": {
    "AssemblyName": "igrORASPConnect420",
    "Culture": null,
    "PublicKeyToken": null,
    "RuntimeVersion": "v4.0.30319",
    "ScanDate": "2026-06-07T12:43:41.669639Z"
  },
  "Dependencies": [
    {
      "AssemblyName": "mscorlib",
      "Version": "4.0.0.0",
      "IsLocalDll": false,
      "ReferencedJsonFile": null
    },
    {
      "AssemblyName": "ISPConnect",
      "Version": "10.0.0.603",
      "IsLocalDll": false,
      "ReferencedJsonFile": null
    },
    {
      "AssemblyName": "Oracle.DataAccess",
      "Version": "4.121.2.0",
      "IsLocalDll": false,
      "ReferencedJsonFile": null
    },
    {
      "AssemblyName": "System.Data",
      "Version": "4.0.0.0",
      "IsLocalDll": false,
      "ReferencedJsonFile": null
    },
    {
      "AssemblyName": "SPCryptServices",
      "Version": "10.0.0.603",
      "IsLocalDll": false,
      "ReferencedJsonFile": null
    },
    {
      "AssemblyName": "System",
      "Version": "4.0.0.0",
      "IsLocalDll": false,
      "ReferencedJsonFile": null
    }
  ],
  "Classes": [
    {
      "Name": "BulkOperation",
      "Namespace": "Ingr.SP2D.ORASPConnect420",
      "FullName": "Ingr.SP2D.ORASPConnect420.BulkOperation",
      "BaseType": "System.Object",
      "IsAbstract": true,
      "IsSealed": false,
      "DeclaringType": null,
      "ImplementedInterfaces": [],
      "Fields": [
        {
          "Name": "S_OK",
          "Type": "System.Int32",
          "IsPublic": false,
          "IsStatic": true,
          "IsReadonly": false,
          "Attributes": []
        },
        {
          "Name": "E_FAIL",
          "Type": "System.Int32",
          "IsPublic": false,
          "IsStatic": true,
          "IsReadonly": false,
          "Attributes": []
        },
        {
          "Name": "MAX_PENDING_ROWS",
          "Type": "System.Int32",
          "IsPublic": false,
          "IsStatic": true,
          "IsReadonly": false,
          "Attributes": []
        },
        {
          "Name": "m_connection",
          "Type": "Ingr.SP2D.ISPConnect.IDBConnection",
          "IsPublic": false,
          "IsStatic": false,
          "IsReadonly": false,
          "Attributes": []
        },
        {
          "Name": "m_lastErrorMessage",
          "Type": "System.String",
          "IsPublic": false,
          "IsStatic": false,
          "IsReadonly": false,
          "Attributes": []
        },
        {
          "Name": "m_sql",
          "Type": "System.String",
          "IsPublic": false,
          "IsStatic": false,
          "IsReadonly": false,
          "Attributes": []
        },
        {
          "Name": "m_columnCount",
          "Type": "System.Int32",
          "IsPublic": false,
          "IsStatic": false,
          "IsReadonly": false,
          "Attributes": []
        },
        {
          "Name": "m_columnTypes",
          "Type": "System.Int32[]",
          "IsPublic": false,
          "IsStatic": false,
          "IsReadonly": false,
          "Attributes": []
        },
        {
          "Name": "m_values",
          "Type": "System.Collections.Generic.List\u00601\u003CSystem.Object[]\u003E",
          "IsPublic": false,
          "IsStatic": false,
          "IsReadonly": false,
          "Attributes": []
        },
        {
          "Name": "m_debugID",
          "Type": "System.String",
          "IsPublic": false,
          "IsStatic": false,
          "IsReadonly": false,
          "Attributes": []
        }
      ],
      "Methods": [
        {
          "Name": ".ctor",
          "ReturnType": "System.Void",
          "IsStatic": false,
          "IsPublic": false,
          "IsVirtual": false,
          "IsAbstract": false,
          "IsConstructor": true,
          "Parameters": [],
          "Attributes": []
        },
        {
          "Name": "Finalize",
          "ReturnType": "System.Void",
          "IsStatic": false,
          "IsPublic": false,
          "IsVirtual": true,
          "IsAbstract": false,
          "IsConstructor": false,
          "Parameters": [],
          "Attributes": []
        },
        {
          "Name": "AddRow",
          "ReturnType": "System.Int32",
          "IsStatic": false,
          "IsPublic": false,
          "IsVirtual": false,
          "IsAbstract": false,
          "IsConstructor": false,
          "Parameters": [
            {
              "Name": "p_data",
              "Type": "System.Object",
              "IsOptional": false,
              "DefaultValue": null,
              "IsOut": false,
              "IsRef": false,
              "Attributes": []
            }
          ],
          "Attributes": []
        },
        {
          "Name": "ClearBuffer",
          "ReturnType": "System.Int32",
          "IsStatic": false,
          "IsPublic": false,
          "IsVirtual": false,
          "IsAbstract": false,
          "IsConstructor": false,
          "Parameters": [],
          "Attributes": []
        },
        {
          "Name": "Flush",
          "ReturnType": "System.Int32",
          "IsStatic": false,
          "IsPublic": false,
          "IsVirtual": false,
          "IsAbstract": false,
          "IsConstructor": false,
          "Parameters": [],
          "Attributes": []
        },
        {
          "Name": "Initialize",
          "ReturnType": "System.Int32",
          "IsStatic": false,
          "IsPublic": false,
          "IsVirtual": false,
          "IsAbstract": false,
          "IsConstructor": false,
          "Parameters": [
            {
              "Name": "p_statement",
              "Type": "System.String",
              "IsOptional": false,
              "DefaultValue": null,
              "IsOut": false,
              "IsRef": false,
              "Attributes": []
            },
            {
              "Name": "p_numOfColumns",
              "Type": "System.Int32",
              "IsOptional": false,
              "DefaultValue": null,
              "IsOut": false,
              "IsRef": false,
              "Attributes": []
            },
            {
              "Name": "p_columnType",
              "Type": "System.Int32[]",
              "IsOptional": false,
              "DefaultValue": null,
              "IsOut": false,
              "IsRef": false,
              "Attributes": []
            }
          ],
          "Attributes": []
        },
        {
          "Name": "PreFlush",
          "ReturnType": "System.Int32",
          "IsStatic": false,
          "IsPublic": false,
          "IsVirtual": true,
          "IsAbstract": false,
          "IsConstructor": false,
          "Parameters": [
            {
              "Name": "p_dbCommand",
              "Type": "Oracle.DataAccess.Client.OracleCommand",
              "IsOptional": false,
              "DefaultValue": null,
              "IsOut": false,
              "IsRef": false,
              "Attributes": []
            }
          ],
          "Attributes": []
        },
        {
          "Name": "PostFlush",
          "ReturnType": "System.Int32",
          "IsStatic": false,
          "IsPublic": false,
          "IsVirtual": true,
          "IsAbstract": false,
          "IsConstructor": false,
          "Parameters": [
            {
              "Name": "p_dbCommand",
              "Type": "Oracle.DataAccess.Client.OracleCommand",
              "IsOptional": false,
              "DefaultValue": null,
              "IsOut": false,
              "IsRef": false,
              "Attributes": []
            },
            {
              "Name": "p_affectedRows",
              "Type": "System.Int32",
              "IsOptional": false,
              "DefaultValue": null,
              "IsOut": false,
              "IsRef": false,
              "Attributes": []
            }
          ],
          "Attributes": []
        }
      ],
      "Properties": [
        {
          "Name": "ColumnCount",
          "Type": "System.Int32",
          "CanRead": true,
          "CanWrite": true
        },
        {
          "Name": "Conn",
          "Type": "Ingr.SP2D.ISPConnect.IDBConnection",
          "CanRead": true,
          "CanWrite": true
        },
        {
          "Name": "DebugID",
          "Type": "System.String",
          "CanRead": true,
          "CanWrite": true
        },
        {
          "Name": "LastErrMsg",
          "Type": "System.String",
          "CanRead": true,
          "CanWrite": true
        },
        {
          "Name": "SqlStatement",
          "Type": "System.String",
          "CanRead": true,
          "CanWrite": true
        },
        {
          "Name": "Values",
          "Type": "System.Collections.Generic.List\u00601\u003CSystem.Object[]\u003E",
          "CanRead": true,
          "CanWrite": false
        }
      ],
      "Events": [],
      "Attributes": []
    },
    {
      "Name": "ORADBBlob",
      "Namespace": "Ingr.SP2D.ORASPConnect420",
      "FullName": "Ingr.SP2D.ORASPConnect420.ORADBBlob",
      "BaseType": "System.Object",
      "IsAbstract": false,
      "IsSealed": false,
      "DeclaringType": null,
      "ImplementedInterfaces": [
        "Ingr.SP2D.ISPConnect.IBlob"
      ],
      "Fields": [
        {
          "Name": "FALSE",
          "Type": "System.Int32",
          "IsPublic": false,
          "IsStatic": true,
          "IsReadonly": false,
          "Attributes": []
        },
        {
          "Name": "TRUE",
          "Type": "System.Int32",
          "IsPublic": false,
          "IsStatic": true,
          "IsReadonly": false,
          "Attributes": []
        },
        {
          "Name": "m_connection",
          "Type": "Ingr.SP2D.ISPConnect.IDBConnection",
          "IsPublic": false,
          "IsStatic": false,
          "IsReadonly": false,
          "Attributes": []
        },
        {
          "Name": "m_lastErrorMessage",
          "Type": "System.String",
          "IsPublic": false,
          "IsStatic": false,
          "IsReadonly": false,
          "Attributes": []
        }
      ],
      "Methods": [
        {
          "Name": ".ctor",
          "ReturnType": "System.Void",
          "IsStatic": false,
          "IsPublic": true,
          "IsVirtual": false,
          "IsAbstract": false,
          "IsConstructor": true,
          "Parameters": [],
          "Attributes": []
        },
        {
          "Name": "Finalize",
          "ReturnType": "System.Void",
          "IsStatic": false,
          "IsPublic": false,
          "IsVirtual": true,
          "IsAbstract": false,
          "IsConstructor": false,
          "Parameters": [],
          "Attributes": []
        },
        {
          "Name": "CopyBlobToFile",
          "ReturnType": "System.Int32",
          "IsStatic": false,
          "IsPublic": true,
          "IsVirtual": true,
          "IsAbstract": false,
          "IsConstructor": false,
          "Parameters": [
            {
              "Name": "p_fileName",
              "Type": "System.String",
              "IsOptional": false,
              "DefaultValue": null,
              "IsOut": false,
              "IsRef": false,
              "Attributes": []
            },
            {
              "Name": "p_tableName",
              "Type": "System.String",
              "IsOptional": false,
              "DefaultValue": null,
              "IsOut": false,
              "IsRef": false,
              "Attributes": []
            },
            {
              "Name": "p_blobColumnName",
              "Type": "System.String",
              "IsOptional": false,
              "DefaultValue": null,
              "IsOut": false,
              "IsRef": false,
              "Attributes": []
            },
            {
              "Name": "p_SPID",
              "Type": "System.String",
              "IsOptional": false,
              "DefaultValue": null,
              "IsOut": false,
              "IsRef": false,
              "Attributes": []
            }
          ],
          "Attributes": []
        },
        {
          "Name": "CopyBlobToFileEx",
          "ReturnType": "System.Int32",
          "IsStatic": false,
          "IsPublic": true,
          "IsVirtual": true,
          "IsAbstract": false,
          "IsConstructor": false,
          "Parameters": [
            {
              "Name": "p_fileName",
              "Type": "System.String",
              "IsOptional": false,
              "DefaultValue": null,
              "IsOut": false,
              "IsRef": false,
              "Attributes": []
            },
            {
              "Name": "p_tableName",
              "Type": "System.String",
              "IsOptional": false,
              "DefaultValue": null,
              "IsOut": false,
              "IsRef": false,
              "Attributes": []
            },
            {
              "Name": "p_blobColumnName",
              "Type": "System.String",
              "IsOptional": false,
              "DefaultValue": null,
              "IsOut": false,
              "IsRef": false,
              "Attributes": []
            },
            {
              "Name": "p_conditionColumnName",
              "Type": "System.String",
              "IsOptional": false,
              "DefaultValue": null,
              "IsOut": false,
              "IsRef": false,
              "Attributes": []
            },
            {
              "Name": "p_conditionValue",
              "Type": "System.String",
              "IsOptional": false,
              "DefaultValue": null,
              "IsOut": false,
              "IsRef": false,
              "Attributes": []
            }
          ],
          "Attributes": []
        },
        {
          "Name": "CopyFileToBlob",
          "ReturnType": "System.Int32",
          "IsStatic": false,
          "IsPublic": true,
          "IsVirtual": true,
          "IsAbstract": false,
          "IsConstructor": false,
          "Parameters": [
            {
              "Name": "p_fileName",
              "Type": "System.String",
              "IsOptional": false,
              "DefaultValue": null,
              "IsOut": false,
              "IsRef": false,
              "Attributes": []
            },
            {
              "Name": "p_tableName",
              "Type": "System.String",
              "IsOptional": false,
              "DefaultValue": null,
              "IsOut": false,
              "IsRef": false,
              "Attributes": []
            },
            {
              "Name": "p_blobColumnName",
              "Type": "System.String",
              "IsOptional": false,
              "DefaultValue": null,
              "IsOut": false,
              "IsRef": false,
              "Attributes": []
            },
            {
              "Name": "p_SPID",
              "Type": "System.String",
              "IsOptional": false,
              "DefaultValue": null,
              "IsOut": false,
              "IsRef": false,
              "Attributes": []
            }
          ],
          "Attributes": []
        },
        {
          "Name": "CopyFileToBlobEx",
          "ReturnType": "System.Int32",
          "IsStatic": false,
          "IsPublic": true,
          "IsVirtual": true,
          "IsAbstract": false,
          "IsConstructor": false,
          "Parameters": [
            {
              "Name": "p_fileName",
              "Type": "System.String",
              "IsOptional": false,
              "DefaultValue": null,
              "IsOut": false,
              "IsRef": false,
              "Attributes": []
            },
            {
              "Name": "p_tableName",
              "Type": "System.String",
              "IsOptional": false,
              "DefaultValue": null,
              "IsOut": false,
              "IsRef": false,
              "Attributes": []
            },
            {
              "Name": "p_blobColumnName",
              "Type": "System.String",
              "IsOptional": false,
              "DefaultValue": null,
              "IsOut": false,
              "IsRef": false,
              "Attributes": []
            },
            {
              "Name": "p_conditionColumnName",
              "Type": "System.String",
              "IsOptional": false,
              "DefaultValue": null,
              "IsOut": false,
              "IsRef": false,
              "Attributes": []
            },
            {
              "Name": "p_conditionValue",
              "Type": "System.String",
              "IsOptional": false,
              "DefaultValue": null,
              "IsOut": false,
              "IsRef": false,
              "Attributes": []
            }
          ],
          "Attributes": []
        },
        {
          "Name": "LoadFileToMemory",
          "ReturnType": "System.Boolean",
          "IsStatic": false,
          "IsPublic": false,
          "IsVirtual": false,
          "IsAbstract": false,
          "IsConstructor": false,
          "Parameters": [
            {
              "Name": "p_fileName",
              "Type": "System.String",
              "IsOptional": false,
              "DefaultValue": null,
              "IsOut": false,
              "IsRef": false,
              "Attributes": []
            },
            {
              "Name": "p_memStream",
              "Type": "System.IO.MemoryStream\u0026",
              "IsOptional": false,
              "DefaultValue": null,
              "IsOut": true,
              "IsRef": true,
              "Attributes": []
            }
          ],
          "Attributes": []
        }
      ],
      "Properties": [
        {
          "Name": "Connection",
          "Type": "Ingr.SP2D.ISPConnect.IDBConnection",
          "CanRead": true,
          "CanWrite": true
        },
        {
          "Name": "LastErrorMessage",
          "Type": "System.String",
          "CanRead": true,
          "CanWrite": true
        }
      ],
      "Events": [],
      "Attributes": []
    },
    {
      "Name": "ORADBBulkCursor",
      "Namespace": "Ingr.SP2D.ORASPConnect420",
      "FullName": "Ingr.SP2D.ORASPConnect420.ORADBBulkCursor",
      "BaseType": "System.Object",
      "IsAbstract": false,
      "IsSealed": false,
      "DeclaringType": null,
      "ImplementedInterfaces": [
        "Ingr.SP2D.ISPConnect.IBulkCursor",
        "System.IDisposable"
      ],
      "Fields": [
        {
          "Name": "FALSE",
          "Type": "System.Int32",
          "IsPublic": false,
          "IsStatic": true,
          "IsReadonly": false,
          "Attributes": []
        },
        {
          "Name": "TRUE",
          "Type": "System.Int32",
          "IsPublic": false,
          "IsStatic": true,
          "IsReadonly": false,
          "Attributes": []
        },
        {
          "Name": "DEFUALT_RECORDS_TO_FETCH",
          "Type": "System.Int32",
          "IsPublic": false,
          "IsStatic": true,
          "IsReadonly": false,
          "Attributes": []
        },
        {
          "Name": "m_disposed",
          "Type": "System.Boolean",
          "IsPublic": false,
          "IsStatic": false,
          "IsReadonly": false,
          "Attributes": []
        },
        {
          "Name": "m_connection",
          "Type": "Ingr.SP2D.ISPConnect.IDBConnection",
          "IsPublic": false,
          "IsStatic": false,
          "IsReadonly": false,
          "Attributes": []
        },
        {
          "Name": "m_lastErrorMessage",
          "Type": "System.String",
          "IsPublic": false,
          "IsStatic": false,
          "IsReadonly": false,
          "Attributes": []
        },
        {
          "Name": "m_bindColumnsCount",
          "Type": "System.Int32",
          "IsPublic": false,
          "IsStatic": false,
          "IsReadonly": false,
          "Attributes": []
        },
        {
          "Name": "m_recordsToFetch",
          "Type": "System.Int32",
          "IsPublic": false,
          "IsStatic": false,
          "IsReadonly": false,
          "Attributes": []
        },
        {
          "Name": "m_sql",
          "Type": "System.String",
          "IsPublic": false,
          "IsStatic": false,
          "IsReadonly": false,
          "Attributes": []
        },
        {
          "Name": "m_command",
          "Type": "Oracle.DataAccess.Client.OracleCommand",
          "IsPublic": false,
          "IsStatic": false,
          "IsReadonly": false,
          "Attributes": []
        },
        {
          "Name": "m_reader",
          "Type": "Oracle.DataAccess.Client.OracleDataReader",
          "IsPublic": false,
          "IsStatic": false,
          "IsReadonly": false,
          "Attributes": []
        },
        {
          "Name": "m_fieldTypeFlags",
          "Type": "System.Collections.Generic.List\u00601\u003CIngr.SP2D.ORASPConnect420.ORADBConnect/RowFieldType\u003E",
          "IsPublic": false,
          "IsStatic": false,
          "IsReadonly": false,
          "Attributes": []
        },
        {
          "Name": "m_queryCount",
          "Type": "System.Int32",
          "IsPublic": false,
          "IsStatic": false,
          "IsReadonly": false,
          "Attributes": []
        }
      ],
      "Methods": [
        {
          "Name": ".ctor",
          "ReturnType": "System.Void",
          "IsStatic": false,
          "IsPublic": true,
          "IsVirtual": false,
          "IsAbstract": false,
          "IsConstructor": true,
          "Parameters": [],
          "Attributes": []
        },
        {
          "Name": "Finalize",
          "ReturnType": "System.Void",
          "IsStatic": false,
          "IsPublic": false,
          "IsVirtual": true,
          "IsAbstract": false,
          "IsConstructor": false,
          "Parameters": [],
          "Attributes": []
        },
        {
          "Name": "GetNextRow",
          "ReturnType": "System.Int32",
          "IsStatic": false,
          "IsPublic": true,
          "IsVirtual": true,
          "IsAbstract": false,
          "IsConstructor": false,
          "Parameters": [
            {
              "Name": "p_data",
              "Type": "System.Object\u0026",
              "IsOptional": false,
              "DefaultValue": null,
              "IsOut": true,
              "IsRef": true,
              "Attributes": []
            }
          ],
          "Attributes": []
        },
        {
          "Name": "GetResults",
          "ReturnType": "System.Int32",
          "IsStatic": false,
          "IsPublic": true,
          "IsVirtual": true,
          "IsAbstract": false,
          "IsConstructor": false,
          "Parameters": [
            {
              "Name": "p_bindValues",
              "Type": "System.Object\u0026",
              "IsOptional": false,
              "DefaultValue": null,
              "IsOut": false,
              "IsRef": true,
              "Attributes": []
            },
            {
              "Name": "p_returnColumnsCount",
              "Type": "System.Int32\u0026",
              "IsOptional": false,
              "DefaultValue": null,
              "IsOut": true,
              "IsRef": true,
              "Attributes": []
            }
          ],
          "Attributes": []
        },
        {
          "Name": "Initialize",
          "ReturnType": "System.Int32",
          "IsStatic": false,
          "IsPublic": true,
          "IsVirtual": true,
          "IsAbstract": false,
          "IsConstructor": false,
          "Parameters": [
            {
              "Name": "p_statement",
              "Type": "System.String",
              "IsOptional": false,
              "DefaultValue": null,
              "IsOut": false,
              "IsRef": false,
              "Attributes": []
            },
            {
              "Name": "p_numOfBindColumns",
              "Type": "System.Int32\u0026",
              "IsOptional": false,
              "DefaultValue": null,
              "IsOut": false,
              "IsRef": true,
              "Attributes": []
            },
            {
              "Name": "p_dataLength",
              "Type": "System.Int32\u0026",
              "IsOptional": false,
              "DefaultValue": null,
              "IsOut": false,
              "IsRef": true,
              "Attributes": []
            },
            {
              "Name": "p_rowBufferSizeIn",
              "Type": "System.Int32\u0026",
              "IsOptional": false,
              "DefaultValue": null,
              "IsOut": false,
              "IsRef": true,
              "Attributes": []
            }
          ],
          "Attributes": []
        },
        {
          "Name": "GetResultsColumnDetails",
          "ReturnType": "System.Int32",
          "IsStatic": false,
          "IsPublic": true,
          "IsVirtual": true,
          "IsAbstract": false,
          "IsConstructor": false,
          "Parameters": [
            {
              "Name": "p_columnDetails",
              "Type": "System.Object\u0026",
              "IsOptional": false,
              "DefaultValue": null,
              "IsOut": true,
              "IsRef": true,
              "Attributes": []
            }
          ],
          "Attributes": []
        },
        {
          "Name": "ReleaseReader",
          "ReturnType": "System.Void",
          "IsStatic": false,
          "IsPublic": false,
          "IsVirtual": false,
          "IsAbstract": false,
          "IsConstructor": false,
          "Parameters": [
            {
              "Name": "p_reader",
              "Type": "Oracle.DataAccess.Client.OracleDataReader\u0026",
              "IsOptional": false,
              "DefaultValue": null,
              "IsOut": false,
              "IsRef": true,
              "Attributes": []
            }
          ],
          "Attributes": []
        },
        {
          "Name": "ReleaseCommand",
          "ReturnType": "System.Void",
          "IsStatic": false,
          "IsPublic": false,
          "IsVirtual": false,
          "IsAbstract": false,
          "IsConstructor": false,
          "Parameters": [
            {
              "Name": "p_cmd",
              "Type": "Oracle.DataAccess.Client.OracleCommand\u0026",
              "IsOptional": false,
              "DefaultValue": null,
              "IsOut": false,
              "IsRef": true,
              "Attributes": []
            }
          ],
          "Attributes": []
        },
        {
          "Name": "Dispose",
          "ReturnType": "System.Void",
          "IsStatic": false,
          "IsPublic": true,
          "IsVirtual": true,
          "IsAbstract": false,
          "IsConstructor": false,
          "Parameters": [],
          "Attributes": []
        },
        {
          "Name": "Dispose",
          "ReturnType": "System.Void",
          "IsStatic": false,
          "IsPublic": false,
          "IsVirtual": true,
          "IsAbstract": false,
          "IsConstructor": false,
          "Parameters": [
            {
              "Name": "p_disposing",
              "Type": "System.Boolean",
              "IsOptional": false,
              "DefaultValue": null,
              "IsOut": false,
              "IsRef": false,
              "Attributes": []
            }
          ],
          "Attributes": []
        }
      ],
      "Properties": [
        {
          "Name": "Connection",
          "Type": "Ingr.SP2D.ISPConnect.IDBConnection",
          "CanRead": true,
          "CanWrite": true
        },
        {
          "Name": "LastErrorMessage",
          "Type": "System.String",
          "CanRead": true,
          "CanWrite": true
        }
      ],
      "Events": [],
      "Attributes": []
    },
    {
      "Name": "ORADBBulkInsert",
      "Namespace": "Ingr.SP2D.ORASPConnect420",
      "FullName": "Ingr.SP2D.ORASPConnect420.ORADBBulkInsert",
      "BaseType": "Ingr.SP2D.ORASPConnect420.BulkOperation",
      "IsAbstract": false,
      "IsSealed": false,
      "DeclaringType": null,
      "ImplementedInterfaces": [
        "Ingr.SP2D.ISPConnect.IBulkInsert"
      ],
      "Fields": [
        {
          "Name": "FALSE",
          "Type": "System.Int32",
          "IsPublic": false,
          "IsStatic": true,
          "IsReadonly": false,
          "Attributes": []
        },
        {
          "Name": "TRUE",
          "Type": "System.Int32",
          "IsPublic": false,
          "IsStatic": true,
          "IsReadonly": false,
          "Attributes": []
        }
      ],
      "Methods": [
        {
          "Name": ".ctor",
          "ReturnType": "System.Void",
          "IsStatic": false,
          "IsPublic": true,
          "IsVirtual": false,
          "IsAbstract": false,
          "IsConstructor": true,
          "Parameters": [],
          "Attributes": []
        },
        {
          "Name": "AddRow",
          "ReturnType": "System.Int32",
          "IsStatic": false,
          "IsPublic": true,
          "IsVirtual": true,
          "IsAbstract": false,
          "IsConstructor": false,
          "Parameters": [
            {
              "Name": "p_data",
              "Type": "System.Object\u0026",
              "IsOptional": false,
              "DefaultValue": null,
              "IsOut": false,
              "IsRef": true,
              "Attributes": []
            }
          ],
          "Attributes": []
        },
        {
          "Name": "ClearBuffer",
          "ReturnType": "System.Int32",
          "IsStatic": false,
          "IsPublic": true,
          "IsVirtual": true,
          "IsAbstract": false,
          "IsConstructor": false,
          "Parameters": [],
          "Attributes": []
        },
        {
          "Name": "Flush",
          "ReturnType": "System.Int32",
          "IsStatic": false,
          "IsPublic": true,
          "IsVirtual": true,
          "IsAbstract": false,
          "IsConstructor": false,
          "Parameters": [],
          "Attributes": []
        },
        {
          "Name": "Initialize",
          "ReturnType": "System.Int32",
          "IsStatic": false,
          "IsPublic": true,
          "IsVirtual": true,
          "IsAbstract": false,
          "IsConstructor": false,
          "Parameters": [
            {
              "Name": "p_statement",
              "Type": "System.String",
              "IsOptional": false,
              "DefaultValue": null,
              "IsOut": false,
              "IsRef": false,
              "Attributes": []
            },
            {
              "Name": "p_columnPosition",
              "Type": "System.Int32\u0026",
              "IsOptional": false,
              "DefaultValue": null,
              "IsOut": false,
              "IsRef": true,
              "Attributes": []
            },
            {
              "Name": "p_inputDataType",
              "Type": "System.Object\u0026",
              "IsOptional": false,
              "DefaultValue": null,
              "IsOut": false,
              "IsRef": true,
              "Attributes": []
            },
            {
              "Name": "p_dataLength",
              "Type": "System.Int32\u0026",
              "IsOptional": false,
              "DefaultValue": null,
              "IsOut": false,
              "IsRef": true,
              "Attributes": []
            }
          ],
          "Attributes": []
        }
      ],
      "Properties": [
        {
          "Name": "Connection",
          "Type": "Ingr.SP2D.ISPConnect.IDBConnection",
          "CanRead": true,
          "CanWrite": true
        },
        {
          "Name": "LastErrorMessage",
          "Type": "System.String",
          "CanRead": true,
          "CanWrite": true
        }
      ],
      "Events": [],
      "Attributes": []
    },
    {
      "Name": "ORADBBulkUpdate",
      "Namespace": "Ingr.SP2D.ORASPConnect420",
      "FullName": "Ingr.SP2D.ORASPConnect420.ORADBBulkUpdate",
      "BaseType": "Ingr.SP2D.ORASPConnect420.BulkOperation",
      "IsAbstract": false,
      "IsSealed": false,
      "DeclaringType": null,
      "ImplementedInterfaces": [
        "Ingr.SP2D.ISPConnect.IBulkUpdate"
      ],
      "Fields": [
        {
          "Name": "S_OK",
          "Type": "System.Int32",
          "IsPublic": false,
          "IsStatic": true,
          "IsReadonly": false,
          "Attributes": []
        },
        {
          "Name": "E_FAIL",
          "Type": "System.Int32",
          "IsPublic": false,
          "IsStatic": true,
          "IsReadonly": false,
          "Attributes": []
        },
        {
          "Name": "ACCESS_DENIED",
          "Type": "System.UInt32",
          "IsPublic": false,
          "IsStatic": true,
          "IsReadonly": false,
          "Attributes": []
        },
        {
          "Name": "m_checkUpdateCount",
          "Type": "System.Boolean",
          "IsPublic": false,
          "IsStatic": false,
          "IsReadonly": false,
          "Attributes": []
        }
      ],
      "Methods": [
        {
          "Name": ".ctor",
          "ReturnType": "System.Void",
          "IsStatic": false,
          "IsPublic": true,
          "IsVirtual": false,
          "IsAbstract": false,
          "IsConstructor": true,
          "Parameters": [],
          "Attributes": []
        },
        {
          "Name": "AddRow",
          "ReturnType": "System.Int32",
          "IsStatic": false,
          "IsPublic": true,
          "IsVirtual": true,
          "IsAbstract": false,
          "IsConstructor": false,
          "Parameters": [
            {
              "Name": "p_data",
              "Type": "System.Object\u0026",
              "IsOptional": false,
              "DefaultValue": null,
              "IsOut": false,
              "IsRef": true,
              "Attributes": []
            }
          ],
          "Attributes": []
        },
        {
          "Name": "ClearBuffer",
          "ReturnType": "System.Int32",
          "IsStatic": false,
          "IsPublic": true,
          "IsVirtual": true,
          "IsAbstract": false,
          "IsConstructor": false,
          "Parameters": [],
          "Attributes": []
        },
        {
          "Name": "Flush",
          "ReturnType": "System.Int32",
          "IsStatic": false,
          "IsPublic": true,
          "IsVirtual": true,
          "IsAbstract": false,
          "IsConstructor": false,
          "Parameters": [],
          "Attributes": []
        },
        {
          "Name": "Initialize",
          "ReturnType": "System.Int32",
          "IsStatic": false,
          "IsPublic": true,
          "IsVirtual": true,
          "IsAbstract": false,
          "IsConstructor": false,
          "Parameters": [
            {
              "Name": "p_statement",
              "Type": "System.String",
              "IsOptional": false,
              "DefaultValue": null,
              "IsOut": false,
              "IsRef": false,
              "Attributes": []
            },
            {
              "Name": "p_checkUpdateCount",
              "Type": "System.Boolean",
              "IsOptional": false,
              "DefaultValue": null,
              "IsOut": false,
              "IsRef": false,
              "Attributes": []
            },
            {
              "Name": "p_numOfColumns",
              "Type": "System.Int32\u0026",
              "IsOptional": false,
              "DefaultValue": null,
              "IsOut": false,
              "IsRef": true,
              "Attributes": []
            },
            {
              "Name": "p_dataLength",
              "Type": "System.Int32\u0026",
              "IsOptional": false,
              "DefaultValue": null,
              "IsOut": false,
              "IsRef": true,
              "Attributes": []
            },
            {
              "Name": "p_inputDataType",
              "Type": "System.Object\u0026",
              "IsOptional": false,
              "DefaultValue": null,
              "IsOut": false,
              "IsRef": true,
              "Attributes": []
            }
          ],
          "Attributes": []
        },
        {
          "Name": "PreFlush",
          "ReturnType": "System.Int32",
          "IsStatic": false,
          "IsPublic": false,
          "IsVirtual": true,
          "IsAbstract": false,
          "IsConstructor": false,
          "Parameters": [
            {
              "Name": "p_dbCommand",
              "Type": "Oracle.DataAccess.Client.OracleCommand",
              "IsOptional": false,
              "DefaultValue": null,
              "IsOut": false,
              "IsRef": false,
              "Attributes": []
            }
          ],
          "Attributes": []
        },
        {
          "Name": "PostFlush",
          "ReturnType": "System.Int32",
          "IsStatic": false,
          "IsPublic": false,
          "IsVirtual": true,
          "IsAbstract": false,
          "IsConstructor": false,
          "Parameters": [
            {
              "Name": "p_dbCommand",
              "Type": "Oracle.DataAccess.Client.OracleCommand",
              "IsOptional": false,
              "DefaultValue": null,
              "IsOut": false,
              "IsRef": false,
              "Attributes": []
            },
            {
              "Name": "p_affectedRows",
              "Type": "System.Int32",
              "IsOptional": false,
              "DefaultValue": null,
              "IsOut": false,
              "IsRef": false,
              "Attributes": []
            }
          ],
          "Attributes": []
        }
      ],
      "Properties": [
        {
          "Name": "Connection",
          "Type": "Ingr.SP2D.ISPConnect.IDBConnection",
          "CanRead": true,
          "CanWrite": true
        },
        {
          "Name": "LastErrorMessage",
          "Type": "System.String",
          "CanRead": true,
          "CanWrite": true
        }
      ],
      "Events": [],
      "Attributes": []
    },
    {
      "Name": "ORADBConnect",
      "Namespace": "Ingr.SP2D.ORASPConnect420",
      "FullName": "Ingr.SP2D.ORASPConnect420.ORADBConnect",
      "BaseType": "System.Object",
      "IsAbstract": false,
      "IsSealed": false,
      "DeclaringType": null,
      "ImplementedInterfaces": [
        "Ingr.SP2D.ISPConnect.IDBConnection",
        "System.IDisposable"
      ],
      "Fields": [
        {
          "Name": "FALSE",
          "Type": "System.Int32",
          "IsPublic": false,
          "IsStatic": true,
          "IsReadonly": false,
          "Attributes": []
        },
        {
          "Name": "TRUE",
          "Type": "System.Int32",
          "IsPublic": false,
          "IsStatic": true,
          "IsReadonly": false,
          "Attributes": []
        },
        {
          "Name": "DEFUALT_RECORDS_TO_FETCH",
          "Type": "System.Int32",
          "IsPublic": false,
          "IsStatic": true,
          "IsReadonly": false,
          "Attributes": []
        },
        {
          "Name": "DEFAULT_COMMAND_TIMEOUT",
          "Type": "System.Int32",
          "IsPublic": false,
          "IsStatic": true,
          "IsReadonly": false,
          "Attributes": []
        },
        {
          "Name": "m_disposed",
          "Type": "System.Boolean",
          "IsPublic": false,
          "IsStatic": false,
          "IsReadonly": false,
          "Attributes": []
        },
        {
          "Name": "m_serverName",
          "Type": "System.String",
          "IsPublic": false,
          "IsStatic": false,
          "IsReadonly": false,
          "Attributes": []
        },
        {
          "Name": "m_transactionInProgress",
          "Type": "System.Boolean",
          "IsPublic": false,
          "IsStatic": false,
          "IsReadonly": false,
          "Attributes": []
        },
        {
          "Name": "m_URL",
          "Type": "System.String",
          "IsPublic": false,
          "IsStatic": false,
          "IsReadonly": false,
          "Attributes": []
        },
        {
          "Name": "m_uid",
          "Type": "System.String",
          "IsPublic": false,
          "IsStatic": false,
          "IsReadonly": false,
          "Attributes": []
        },
        {
          "Name": "m_pwd",
          "Type": "System.String",
          "IsPublic": false,
          "IsStatic": false,
          "IsReadonly": false,
          "Attributes": []
        },
        {
          "Name": "m_numberRowsAffected",
          "Type": "System.Int32",
          "IsPublic": false,
          "IsStatic": false,
          "IsReadonly": false,
          "Attributes": []
        },
        {
          "Name": "m_database",
          "Type": "System.String",
          "IsPublic": false,
          "IsStatic": false,
          "IsReadonly": false,
          "Attributes": []
        },
        {
          "Name": "m_lastErrorMessage",
          "Type": "System.String",
          "IsPublic": false,
          "IsStatic": false,
          "IsReadonly": false,
          "Attributes": []
        },
        {
          "Name": "m_connection",
          "Type": "Oracle.DataAccess.Client.OracleConnection",
          "IsPublic": false,
          "IsStatic": false,
          "IsReadonly": false,
          "Attributes": []
        },
        {
          "Name": "m_command",
          "Type": "Oracle.DataAccess.Client.OracleCommand",
          "IsPublic": false,
          "IsStatic": false,
          "IsReadonly": false,
          "Attributes": []
        },
        {
          "Name": "m_reader",
          "Type": "Oracle.DataAccess.Client.OracleDataReader",
          "IsPublic": false,
          "IsStatic": false,
          "IsReadonly": false,
          "Attributes": []
        },
        {
          "Name": "m_txn",
          "Type": "Oracle.DataAccess.Client.OracleTransaction",
          "IsPublic": false,
          "IsStatic": false,
          "IsReadonly": false,
          "Attributes": []
        },
        {
          "Name": "m_pooling",
          "Type": "System.Boolean",
          "IsPublic": false,
          "IsStatic": false,
          "IsReadonly": false,
          "Attributes": []
        },
        {
          "Name": "m_CommandTimeout",
          "Type": "System.Int32",
          "IsPublic": false,
          "IsStatic": false,
          "IsReadonly": false,
          "Attributes": []
        },
        {
          "Name": "m_fieldTypeFlags",
          "Type": "System.Collections.Generic.List\u00601\u003CIngr.SP2D.ORASPConnect420.ORADBConnect/RowFieldType\u003E",
          "IsPublic": false,
          "IsStatic": false,
          "IsReadonly": false,
          "Attributes": []
        },
        {
          "Name": "m_connectionStringTemplate",
          "Type": "System.String",
          "IsPublic": false,
          "IsStatic": false,
          "IsReadonly": false,
          "Attributes": []
        }
      ],
      "Methods": [
        {
          "Name": ".ctor",
          "ReturnType": "System.Void",
          "IsStatic": false,
          "IsPublic": true,
          "IsVirtual": false,
          "IsAbstract": false,
          "IsConstructor": true,
          "Parameters": [],
          "Attributes": []
        },
        {
          "Name": "Finalize",
          "ReturnType": "System.Void",
          "IsStatic": false,
          "IsPublic": false,
          "IsVirtual": true,
          "IsAbstract": false,
          "IsConstructor": false,
          "Parameters": [],
          "Attributes": []
        },
        {
          "Name": "BeginTransaction",
          "ReturnType": "System.Int32",
          "IsStatic": false,
          "IsPublic": true,
          "IsVirtual": true,
          "IsAbstract": false,
          "IsConstructor": false,
          "Parameters": [],
          "Attributes": []
        },
        {
          "Name": "BeginTransactionEx",
          "ReturnType": "System.Int32",
          "IsStatic": false,
          "IsPublic": true,
          "IsVirtual": true,
          "IsAbstract": false,
          "IsConstructor": false,
          "Parameters": [
            {
              "Name": "p_transactionIsolationLevel",
              "Type": "System.Int32\u0026",
              "IsOptional": false,
              "DefaultValue": null,
              "IsOut": false,
              "IsRef": true,
              "Attributes": []
            }
          ],
          "Attributes": []
        },
        {
          "Name": "Close",
          "ReturnType": "System.Int32",
          "IsStatic": false,
          "IsPublic": true,
          "IsVirtual": true,
          "IsAbstract": false,
          "IsConstructor": false,
          "Parameters": [],
          "Attributes": []
        },
        {
          "Name": "Connect",
          "ReturnType": "System.Int32",
          "IsStatic": false,
          "IsPublic": true,
          "IsVirtual": true,
          "IsAbstract": false,
          "IsConstructor": false,
          "Parameters": [],
          "Attributes": []
        },
        {
          "Name": "DetachTransaction",
          "ReturnType": "System.Int32",
          "IsStatic": false,
          "IsPublic": true,
          "IsVirtual": true,
          "IsAbstract": false,
          "IsConstructor": false,
          "Parameters": [],
          "Attributes": []
        },
        {
          "Name": "EndTransaction",
          "ReturnType": "System.Int32",
          "IsStatic": false,
          "IsPublic": true,
          "IsVirtual": true,
          "IsAbstract": false,
          "IsConstructor": false,
          "Parameters": [],
          "Attributes": []
        },
        {
          "Name": "ExecuteCommand",
          "ReturnType": "System.Int32",
          "IsStatic": false,
          "IsPublic": true,
          "IsVirtual": true,
          "IsAbstract": false,
          "IsConstructor": false,
          "Parameters": [
            {
              "Name": "p_statement",
              "Type": "System.String",
              "IsOptional": false,
              "DefaultValue": null,
              "IsOut": false,
              "IsRef": false,
              "Attributes": []
            }
          ],
          "Attributes": []
        },
        {
          "Name": "ExecuteCommandEX",
          "ReturnType": "System.Int32",
          "IsStatic": false,
          "IsPublic": true,
          "IsVirtual": true,
          "IsAbstract": false,
          "IsConstructor": false,
          "Parameters": [
            {
              "Name": "p_statement",
              "Type": "System.String",
              "IsOptional": false,
              "DefaultValue": null,
              "IsOut": false,
              "IsRef": false,
              "Attributes": []
            }
          ],
          "Attributes": []
        },
        {
          "Name": "GetBoundResults",
          "ReturnType": "System.Int32",
          "IsStatic": false,
          "IsPublic": true,
          "IsVirtual": true,
          "IsAbstract": false,
          "IsConstructor": false,
          "Parameters": [
            {
              "Name": "p_query",
              "Type": "System.String",
              "IsOptional": false,
              "DefaultValue": null,
              "IsOut": false,
              "IsRef": false,
              "Attributes": []
            },
            {
              "Name": "p_numBinds",
              "Type": "System.Int32\u0026",
              "IsOptional": false,
              "DefaultValue": null,
              "IsOut": false,
              "IsRef": true,
              "Attributes": []
            },
            {
              "Name": "p_bindTypes",
              "Type": "System.Int32\u0026",
              "IsOptional": false,
              "DefaultValue": null,
              "IsOut": false,
              "IsRef": true,
              "Attributes": []
            },
            {
              "Name": "p_bindValues",
              "Type": "System.Object\u0026",
              "IsOptional": false,
              "DefaultValue": null,
              "IsOut": false,
              "IsRef": true,
              "Attributes": []
            },
            {
              "Name": "p_colCount",
              "Type": "System.Int32\u0026",
              "IsOptional": false,
              "DefaultValue": null,
              "IsOut": true,
              "IsRef": true,
              "Attributes": []
            },
            {
              "Name": "p_rows",
              "Type": "System.Int32\u0026",
              "IsOptional": false,
              "DefaultValue": null,
              "IsOut": false,
              "IsRef": true,
              "Attributes": []
            }
          ],
          "Attributes": []
        },
        {
          "Name": "GetNextRow",
          "ReturnType": "System.Int32",
          "IsStatic": false,
          "IsPublic": true,
          "IsVirtual": true,
          "IsAbstract": false,
          "IsConstructor": false,
          "Parameters": [
            {
              "Name": "p_data",
              "Type": "System.Object\u0026",
              "IsOptional": false,
              "DefaultValue": null,
              "IsOut": true,
              "IsRef": true,
              "Attributes": []
            }
          ],
          "Attributes": []
        },
        {
          "Name": "GetResults",
          "ReturnType": "System.Int32",
          "IsStatic": false,
          "IsPublic": true,
          "IsVirtual": true,
          "IsAbstract": false,
          "IsConstructor": false,
          "Parameters": [
            {
              "Name": "p_query",
              "Type": "System.String",
              "IsOptional": false,
              "DefaultValue": null,
              "IsOut": false,
              "IsRef": false,
              "Attributes": []
            },
            {
              "Name": "p_colCount",
              "Type": "System.Int32\u0026",
              "IsOptional": false,
              "DefaultValue": null,
              "IsOut": true,
              "IsRef": true,
              "Attributes": []
            },
            {
              "Name": "p_rows",
              "Type": "System.Int32\u0026",
              "IsOptional": false,
              "DefaultValue": null,
              "IsOut": false,
              "IsRef": true,
              "Attributes": []
            }
          ],
          "Attributes": []
        },
        {
          "Name": "GetResultsColumnDetails",
          "ReturnType": "System.Int32",
          "IsStatic": false,
          "IsPublic": true,
          "IsVirtual": true,
          "IsAbstract": false,
          "IsConstructor": false,
          "Parameters": [
            {
              "Name": "p_columnDetails",
              "Type": "System.Object\u0026",
              "IsOptional": false,
              "DefaultValue": null,
              "IsOut": true,
              "IsRef": true,
              "Attributes": []
            }
          ],
          "Attributes": []
        },
        {
          "Name": "ResumeTransaction",
          "ReturnType": "System.Int32",
          "IsStatic": false,
          "IsPublic": true,
          "IsVirtual": true,
          "IsAbstract": false,
          "IsConstructor": false,
          "Parameters": [],
          "Attributes": []
        },
        {
          "Name": "RollbackTransaction",
          "ReturnType": "System.Int32",
          "IsStatic": false,
          "IsPublic": true,
          "IsVirtual": true,
          "IsAbstract": false,
          "IsConstructor": false,
          "Parameters": [],
          "Attributes": []
        },
        {
          "Name": "SetCommandTimeout",
          "ReturnType": "System.Int32",
          "IsStatic": false,
          "IsPublic": true,
          "IsVirtual": true,
          "IsAbstract": false,
          "IsConstructor": false,
          "Parameters": [
            {
              "Name": "p_nextExecuteTimeout",
              "Type": "System.Int32",
              "IsOptional": false,
              "DefaultValue": null,
              "IsOut": false,
              "IsRef": false,
              "Attributes": []
            }
          ],
          "Attributes": []
        },
        {
          "Name": "CheckSQLerr",
          "ReturnType": "System.String",
          "IsStatic": false,
          "IsPublic": true,
          "IsVirtual": false,
          "IsAbstract": false,
          "IsConstructor": false,
          "Parameters": [
            {
              "Name": "p_ex",
              "Type": "System.Exception",
              "IsOptional": false,
              "DefaultValue": null,
              "IsOut": false,
              "IsRef": false,
              "Attributes": []
            }
          ],
          "Attributes": []
        },
        {
          "Name": "CollectColumnDetails",
          "ReturnType": "System.Data.DataTable",
          "IsStatic": true,
          "IsPublic": false,
          "IsVirtual": false,
          "IsAbstract": false,
          "IsConstructor": false,
          "Parameters": [
            {
              "Name": "p_reader",
              "Type": "Oracle.DataAccess.Client.OracleDataReader",
              "IsOptional": false,
              "DefaultValue": null,
              "IsOut": false,
              "IsRef": false,
              "Attributes": []
            }
          ],
          "Attributes": []
        },
        {
          "Name": "LogBSTRMsg",
          "ReturnType": "System.Void",
          "IsStatic": false,
          "IsPublic": false,
          "IsVirtual": false,
          "IsAbstract": false,
          "IsConstructor": false,
          "Parameters": [
            {
              "Name": "p_msg",
              "Type": "System.String",
              "IsOptional": false,
              "DefaultValue": null,
              "IsOut": false,
              "IsRef": false,
              "Attributes": []
            }
          ],
          "Attributes": []
        },
        {
          "Name": "GetCustomConnectString",
          "ReturnType": "System.String",
          "IsStatic": false,
          "IsPublic": false,
          "IsVirtual": false,
          "IsAbstract": false,
          "IsConstructor": false,
          "Parameters": [
            {
              "Name": "p_CurrentConnctString",
              "Type": "System.String",
              "IsOptional": false,
              "DefaultValue": null,
              "IsOut": false,
              "IsRef": false,
              "Attributes": []
            },
            {
              "Name": "p_EnvConnectString",
              "Type": "System.String",
              "IsOptional": false,
              "DefaultValue": null,
              "IsOut": false,
              "IsRef": false,
              "Attributes": []
            }
          ],
          "Attributes": []
        },
        {
          "Name": "GetEnvConnectionStringExtension",
          "ReturnType": "System.String",
          "IsStatic": false,
          "IsPublic": false,
          "IsVirtual": false,
          "IsAbstract": false,
          "IsConstructor": false,
          "Parameters": [],
          "Attributes": []
        },
        {
          "Name": "GetPlainTextPassword",
          "ReturnType": "System.String",
          "IsStatic": false,
          "IsPublic": false,
          "IsVirtual": false,
          "IsAbstract": false,
          "IsConstructor": false,
          "Parameters": [
            {
              "Name": "p_securePwd",
              "Type": "System.Security.SecureString",
              "IsOptional": false,
              "DefaultValue": null,
              "IsOut": false,
              "IsRef": false,
              "Attributes": []
            }
          ],
          "Attributes": []
        },
        {
          "Name": "ReleaseConnection",
          "ReturnType": "System.Void",
          "IsStatic": false,
          "IsPublic": false,
          "IsVirtual": false,
          "IsAbstract": false,
          "IsConstructor": false,
          "Parameters": [
            {
              "Name": "p_conn",
              "Type": "Oracle.DataAccess.Client.OracleConnection",
              "IsOptional": false,
              "DefaultValue": null,
              "IsOut": false,
              "IsRef": false,
              "Attributes": []
            }
          ],
          "Attributes": []
        },
        {
          "Name": "ReleaseReader",
          "ReturnType": "System.Void",
          "IsStatic": true,
          "IsPublic": false,
          "IsVirtual": false,
          "IsAbstract": false,
          "IsConstructor": false,
          "Parameters": [
            {
              "Name": "p_reader",
              "Type": "Oracle.DataAccess.Client.OracleDataReader\u0026",
              "IsOptional": false,
              "DefaultValue": null,
              "IsOut": false,
              "IsRef": true,
              "Attributes": []
            }
          ],
          "Attributes": []
        },
        {
          "Name": "ReleaseCommand",
          "ReturnType": "System.Void",
          "IsStatic": true,
          "IsPublic": false,
          "IsVirtual": false,
          "IsAbstract": false,
          "IsConstructor": false,
          "Parameters": [
            {
              "Name": "p_cmd",
              "Type": "Oracle.DataAccess.Client.OracleCommand\u0026",
              "IsOptional": false,
              "DefaultValue": null,
              "IsOut": false,
              "IsRef": true,
              "Attributes": []
            }
          ],
          "Attributes": []
        },
        {
          "Name": "TypeOfLongFields",
          "ReturnType": "System.Boolean[]",
          "IsStatic": true,
          "IsPublic": false,
          "IsVirtual": false,
          "IsAbstract": false,
          "IsConstructor": false,
          "Parameters": [
            {
              "Name": "p_reader",
              "Type": "Oracle.DataAccess.Client.OracleDataReader\u0026",
              "IsOptional": false,
              "DefaultValue": null,
              "IsOut": false,
              "IsRef": true,
              "Attributes": []
            }
          ],
          "Attributes": []
        },
        {
          "Name": "TypeOfFloatFields",
          "ReturnType": "System.Boolean[]",
          "IsStatic": true,
          "IsPublic": false,
          "IsVirtual": false,
          "IsAbstract": false,
          "IsConstructor": false,
          "Parameters": [
            {
              "Name": "p_reader",
              "Type": "Oracle.DataAccess.Client.OracleDataReader\u0026",
              "IsOptional": false,
              "DefaultValue": null,
              "IsOut": false,
              "IsRef": true,
              "Attributes": []
            }
          ],
          "Attributes": []
        },
        {
          "Name": "TypeOfFields",
          "ReturnType": "System.Void",
          "IsStatic": true,
          "IsPublic": false,
          "IsVirtual": false,
          "IsAbstract": false,
          "IsConstructor": false,
          "Parameters": [
            {
              "Name": "p_reader",
              "Type": "Oracle.DataAccess.Client.OracleDataReader\u0026",
              "IsOptional": false,
              "DefaultValue": null,
              "IsOut": false,
              "IsRef": true,
              "Attributes": []
            },
            {
              "Name": "p_fieldFlags",
              "Type": "System.Collections.Generic.List\u00601\u003CIngr.SP2D.ORASPConnect420.ORADBConnect/RowFieldType\u003E\u0026",
              "IsOptional": false,
              "DefaultValue": null,
              "IsOut": false,
              "IsRef": true,
              "Attributes": []
            }
          ],
          "Attributes": []
        },
        {
          "Name": "ResetCommandTimeout",
          "ReturnType": "System.Void",
          "IsStatic": false,
          "IsPublic": false,
          "IsVirtual": false,
          "IsAbstract": false,
          "IsConstructor": false,
          "Parameters": [],
          "Attributes": []
        },
        {
          "Name": "DeferConstraints",
          "ReturnType": "System.Void",
          "IsStatic": false,
          "IsPublic": false,
          "IsVirtual": false,
          "IsAbstract": false,
          "IsConstructor": false,
          "Parameters": [],
          "Attributes": []
        },
        {
          "Name": "Dispose",
          "ReturnType": "System.Void",
          "IsStatic": false,
          "IsPublic": true,
          "IsVirtual": true,
          "IsAbstract": false,
          "IsConstructor": false,
          "Parameters": [],
          "Attributes": []
        },
        {
          "Name": "Dispose",
          "ReturnType": "System.Void",
          "IsStatic": false,
          "IsPublic": false,
          "IsVirtual": true,
          "IsAbstract": false,
          "IsConstructor": false,
          "Parameters": [
            {
              "Name": "p_disposing",
              "Type": "System.Boolean",
              "IsOptional": false,
              "DefaultValue": null,
              "IsOut": false,
              "IsRef": false,
              "Attributes": []
            }
          ],
          "Attributes": []
        }
      ],
      "Properties": [
        {
          "Name": "Database",
          "Type": "System.String",
          "CanRead": true,
          "CanWrite": true
        },
        {
          "Name": "LastErrorMessage",
          "Type": "System.String",
          "CanRead": true,
          "CanWrite": true
        },
        {
          "Name": "NumberRowsAffected",
          "Type": "System.Int32",
          "CanRead": true,
          "CanWrite": false
        },
        {
          "Name": "Pwd",
          "Type": "System.String",
          "CanRead": true,
          "CanWrite": true
        },
        {
          "Name": "ServerName",
          "Type": "System.String",
          "CanRead": true,
          "CanWrite": true
        },
        {
          "Name": "TransactionInProgress",
          "Type": "System.Boolean",
          "CanRead": true,
          "CanWrite": false
        },
        {
          "Name": "URL",
          "Type": "System.String",
          "CanRead": true,
          "CanWrite": true
        },
        {
          "Name": "Uid",
          "Type": "System.String",
          "CanRead": true,
          "CanWrite": true
        },
        {
          "Name": "Pooling",
          "Type": "System.Boolean",
          "CanRead": true,
          "CanWrite": true
        },
        {
          "Name": "CommandTimeout",
          "Type": "System.Int32",
          "CanRead": true,
          "CanWrite": false
        },
        {
          "Name": "Connection",
          "Type": "Oracle.DataAccess.Client.OracleConnection",
          "CanRead": true,
          "CanWrite": false
        },
        {
          "Name": "Transaction",
          "Type": "Oracle.DataAccess.Client.OracleTransaction",
          "CanRead": true,
          "CanWrite": false
        }
      ],
      "Events": [],
      "Attributes": []
    },
    {
      "Name": "ORADBResultSet",
      "Namespace": "Ingr.SP2D.ORASPConnect420",
      "FullName": "Ingr.SP2D.ORASPConnect420.ORADBResultSet",
      "BaseType": "System.Object",
      "IsAbstract": false,
      "IsSealed": false,
      "DeclaringType": null,
      "ImplementedInterfaces": [
        "Ingr.SP2D.ISPConnect.IResultSet"
      ],
      "Fields": [
        {
          "Name": "S_OK",
          "Type": "System.Int32",
          "IsPublic": false,
          "IsStatic": true,
          "IsReadonly": false,
          "Attributes": []
        },
        {
          "Name": "E_FAIL",
          "Type": "System.Int32",
          "IsPublic": false,
          "IsStatic": true,
          "IsReadonly": false,
          "Attributes": []
        },
        {
          "Name": "m_disposed",
          "Type": "System.Boolean",
          "IsPublic": false,
          "IsStatic": false,
          "IsReadonly": false,
          "Attributes": []
        },
        {
          "Name": "m_lastErrorMessage",
          "Type": "System.String",
          "IsPublic": false,
          "IsStatic": false,
          "IsReadonly": false,
          "Attributes": []
        },
        {
          "Name": "m_connection",
          "Type": "Ingr.SP2D.ISPConnect.IDBConnection",
          "IsPublic": false,
          "IsStatic": false,
          "IsReadonly": false,
          "Attributes": []
        },
        {
          "Name": "m_reader",
          "Type": "Oracle.DataAccess.Client.OracleDataReader",
          "IsPublic": false,
          "IsStatic": false,
          "IsReadonly": false,
          "Attributes": []
        },
        {
          "Name": "m_command",
          "Type": "Oracle.DataAccess.Client.OracleCommand",
          "IsPublic": false,
          "IsStatic": false,
          "IsReadonly": false,
          "Attributes": []
        },
        {
          "Name": "m_firstGetValue",
          "Type": "System.Boolean",
          "IsPublic": false,
          "IsStatic": false,
          "IsReadonly": false,
          "Attributes": []
        },
        {
          "Name": "m_longFlags",
          "Type": "System.Boolean[]",
          "IsPublic": false,
          "IsStatic": false,
          "IsReadonly": false,
          "Attributes": []
        }
      ],
      "Methods": [
        {
          "Name": ".ctor",
          "ReturnType": "System.Void",
          "IsStatic": false,
          "IsPublic": true,
          "IsVirtual": false,
          "IsAbstract": false,
          "IsConstructor": true,
          "Parameters": [],
          "Attributes": []
        },
        {
          "Name": "Finalize",
          "ReturnType": "System.Void",
          "IsStatic": false,
          "IsPublic": false,
          "IsVirtual": true,
          "IsAbstract": false,
          "IsConstructor": false,
          "Parameters": [],
          "Attributes": []
        },
        {
          "Name": "BeginTransaction",
          "ReturnType": "System.Int32",
          "IsStatic": false,
          "IsPublic": true,
          "IsVirtual": true,
          "IsAbstract": false,
          "IsConstructor": false,
          "Parameters": [],
          "Attributes": []
        },
        {
          "Name": "ColumnDef",
          "ReturnType": "System.Int32",
          "IsStatic": false,
          "IsPublic": true,
          "IsVirtual": true,
          "IsAbstract": false,
          "IsConstructor": false,
          "Parameters": [
            {
              "Name": "p_columnNames",
              "Type": "System.Object\u0026",
              "IsOptional": false,
              "DefaultValue": null,
              "IsOut": true,
              "IsRef": true,
              "Attributes": []
            },
            {
              "Name": "p_columnTypes",
              "Type": "System.Object\u0026",
              "IsOptional": false,
              "DefaultValue": null,
              "IsOut": true,
              "IsRef": true,
              "Attributes": []
            },
            {
              "Name": "p_columnCount",
              "Type": "System.Int32\u0026",
              "IsOptional": false,
              "DefaultValue": null,
              "IsOut": true,
              "IsRef": true,
              "Attributes": []
            }
          ],
          "Attributes": []
        },
        {
          "Name": "EndTransaction",
          "ReturnType": "System.Int32",
          "IsStatic": false,
          "IsPublic": true,
          "IsVirtual": true,
          "IsAbstract": false,
          "IsConstructor": false,
          "Parameters": [],
          "Attributes": []
        },
        {
          "Name": "ExecuteParam",
          "ReturnType": "System.Int32",
          "IsStatic": false,
          "IsPublic": true,
          "IsVirtual": true,
          "IsAbstract": false,
          "IsConstructor": false,
          "Parameters": [
            {
              "Name": "p_query",
              "Type": "System.String",
              "IsOptional": false,
              "DefaultValue": null,
              "IsOut": false,
              "IsRef": false,
              "Attributes": []
            },
            {
              "Name": "p_numBinds",
              "Type": "System.Int32\u0026",
              "IsOptional": false,
              "DefaultValue": null,
              "IsOut": false,
              "IsRef": true,
              "Attributes": []
            },
            {
              "Name": "p_bindTypes",
              "Type": "System.Int32\u0026",
              "IsOptional": false,
              "DefaultValue": null,
              "IsOut": false,
              "IsRef": true,
              "Attributes": []
            },
            {
              "Name": "p_bindValues",
              "Type": "System.Object\u0026",
              "IsOptional": false,
              "DefaultValue": null,
              "IsOut": false,
              "IsRef": true,
              "Attributes": []
            },
            {
              "Name": "p_colCount",
              "Type": "System.Int32\u0026",
              "IsOptional": false,
              "DefaultValue": null,
              "IsOut": true,
              "IsRef": true,
              "Attributes": []
            },
            {
              "Name": "p_rows",
              "Type": "System.Int32\u0026",
              "IsOptional": false,
              "DefaultValue": null,
              "IsOut": false,
              "IsRef": true,
              "Attributes": []
            }
          ],
          "Attributes": []
        },
        {
          "Name": "GetValue",
          "ReturnType": "System.Int32",
          "IsStatic": false,
          "IsPublic": true,
          "IsVirtual": true,
          "IsAbstract": false,
          "IsConstructor": false,
          "Parameters": [
            {
              "Name": "p_columnName",
              "Type": "System.String",
              "IsOptional": false,
              "DefaultValue": null,
              "IsOut": false,
              "IsRef": false,
              "Attributes": []
            },
            {
              "Name": "p_data",
              "Type": "System.Object\u0026",
              "IsOptional": false,
              "DefaultValue": null,
              "IsOut": true,
              "IsRef": true,
              "Attributes": []
            }
          ],
          "Attributes": []
        },
        {
          "Name": "MoveNext",
          "ReturnType": "System.Int32",
          "IsStatic": false,
          "IsPublic": true,
          "IsVirtual": true,
          "IsAbstract": false,
          "IsConstructor": false,
          "Parameters": [],
          "Attributes": []
        },
        {
          "Name": "Retrieve",
          "ReturnType": "System.Int32",
          "IsStatic": false,
          "IsPublic": true,
          "IsVirtual": true,
          "IsAbstract": false,
          "IsConstructor": false,
          "Parameters": [
            {
              "Name": "p_query",
              "Type": "System.String",
              "IsOptional": false,
              "DefaultValue": null,
              "IsOut": false,
              "IsRef": false,
              "Attributes": []
            },
            {
              "Name": "p_colCount",
              "Type": "System.Int32\u0026",
              "IsOptional": false,
              "DefaultValue": null,
              "IsOut": true,
              "IsRef": true,
              "Attributes": []
            },
            {
              "Name": "p_rows",
              "Type": "System.Int32\u0026",
              "IsOptional": false,
              "DefaultValue": null,
              "IsOut": false,
              "IsRef": true,
              "Attributes": []
            }
          ],
          "Attributes": []
        },
        {
          "Name": "RollbackTransaction",
          "ReturnType": "System.Int32",
          "IsStatic": false,
          "IsPublic": true,
          "IsVirtual": true,
          "IsAbstract": false,
          "IsConstructor": false,
          "Parameters": [],
          "Attributes": []
        },
        {
          "Name": "Close",
          "ReturnType": "System.Int32",
          "IsStatic": false,
          "IsPublic": true,
          "IsVirtual": true,
          "IsAbstract": false,
          "IsConstructor": false,
          "Parameters": [],
          "Attributes": []
        },
        {
          "Name": "Dispose",
          "ReturnType": "System.Void",
          "IsStatic": false,
          "IsPublic": true,
          "IsVirtual": false,
          "IsAbstract": false,
          "IsConstructor": false,
          "Parameters": [],
          "Attributes": []
        },
        {
          "Name": "Dispose",
          "ReturnType": "System.Void",
          "IsStatic": false,
          "IsPublic": false,
          "IsVirtual": true,
          "IsAbstract": false,
          "IsConstructor": false,
          "Parameters": [
            {
              "Name": "p_disposing",
              "Type": "System.Boolean",
              "IsOptional": false,
              "DefaultValue": null,
              "IsOut": false,
              "IsRef": false,
              "Attributes": []
            }
          ],
          "Attributes": []
        }
      ],
      "Properties": [
        {
          "Name": "Connection",
          "Type": "Ingr.SP2D.ISPConnect.IDBConnection",
          "CanRead": true,
          "CanWrite": true
        },
        {
          "Name": "LastErrorMessage",
          "Type": "System.String",
          "CanRead": true,
          "CanWrite": true
        },
        {
          "Name": "NumberRowsAffected",
          "Type": "System.Int32",
          "CanRead": true,
          "CanWrite": true
        }
      ],
      "Events": [],
      "Attributes": []
    }
  ],
  "Interfaces": [],
  "Structs": [],
  "Enums": [
    {
      "Name": "RowFieldType",
      "Namespace": "",
      "FullName": "Ingr.SP2D.ORASPConnect420.ORADBConnect/RowFieldType",
      "DeclaringType": "Ingr.SP2D.ORASPConnect420.ORADBConnect",
      "Values": [
        "Other",
        "Int",
        "Float"
      ]
    }
  ],
  "Delegates": []
}