{
  "Id": "5dba60a1-240f-4663-92db-1d3cb672e2a4",
  "DllName": "igrTimeConvert412",
  "Version": "10.0.0.603",
  "FilePath": "D:\\Off-Share\\P\u0026ID Workstation\\bin\\igrTimeConvert412.dll",
  "Metadata": {
    "AssemblyName": "igrTimeConvert412",
    "Culture": null,
    "PublicKeyToken": null,
    "RuntimeVersion": "v4.0.30319",
    "ScanDate": "2026-06-07T12:43:41.669639Z"
  },
  "Dependencies": [
    {
      "AssemblyName": "mscorlib",
      "Version": "4.0.0.0",
      "IsLocalDll": false,
      "ReferencedJsonFile": null
    },
    {
      "AssemblyName": "Microsoft.VisualBasic",
      "Version": "10.0.0.0",
      "IsLocalDll": false,
      "ReferencedJsonFile": null
    },
    {
      "AssemblyName": "GalilCs.Transposition.Extensions",
      "Version": "10.0.0.603",
      "IsLocalDll": false,
      "ReferencedJsonFile": null
    },
    {
      "AssemblyName": "igrSP2DErrLog420",
      "Version": "10.0.0.603",
      "IsLocalDll": false,
      "ReferencedJsonFile": null
    }
  ],
  "Classes": [
    {
      "Name": "TimeConvert",
      "Namespace": "Ingr.SP2D.igrTimeConvert412",
      "FullName": "Ingr.SP2D.igrTimeConvert412.TimeConvert",
      "BaseType": "System.Object",
      "IsAbstract": false,
      "IsSealed": false,
      "DeclaringType": null,
      "ImplementedInterfaces": [],
      "Fields": [
        {
          "Name": "TIME_ZONE_ID_UNKNOWN",
          "Type": "System.Int32",
          "IsPublic": false,
          "IsStatic": true,
          "IsReadonly": false,
          "Attributes": []
        },
        {
          "Name": "TIME_ZONE_ID_STANDARD",
          "Type": "System.Int32",
          "IsPublic": false,
          "IsStatic": true,
          "IsReadonly": false,
          "Attributes": []
        },
        {
          "Name": "TIME_ZONE_ID_INVALID",
          "Type": "System.Int32",
          "IsPublic": false,
          "IsStatic": true,
          "IsReadonly": false,
          "Attributes": []
        },
        {
          "Name": "TIME_ZONE_ID_DAYLIGHT",
          "Type": "System.Int32",
          "IsPublic": false,
          "IsStatic": true,
          "IsReadonly": false,
          "Attributes": []
        }
      ],
      "Methods": [
        {
          "Name": "LocalTimeZone",
          "ReturnType": "System.Object",
          "IsStatic": false,
          "IsPublic": false,
          "IsVirtual": false,
          "IsAbstract": false,
          "IsConstructor": false,
          "Parameters": [
            {
              "Name": "ReturnValue",
              "Type": "Ingr.SP2D.igrTimeConvert412.TimeConvert/TimeZoneReturn\u0026",
              "IsOptional": false,
              "DefaultValue": null,
              "IsOut": false,
              "IsRef": true,
              "Attributes": []
            }
          ],
          "Attributes": []
        },
        {
          "Name": "ConvertLocalToGMT",
          "ReturnType": "System.DateTime",
          "IsStatic": false,
          "IsPublic": true,
          "IsVirtual": false,
          "IsAbstract": false,
          "IsConstructor": false,
          "Parameters": [
            {
              "Name": "LocalDate",
              "Type": "System.DateTime",
              "IsOptional": false,
              "DefaultValue": null,
              "IsOut": false,
              "IsRef": false,
              "Attributes": []
            }
          ],
          "Attributes": []
        },
        {
          "Name": "ConvertGMTToLocal",
          "ReturnType": "System.DateTime",
          "IsStatic": false,
          "IsPublic": true,
          "IsVirtual": false,
          "IsAbstract": false,
          "IsConstructor": false,
          "Parameters": [
            {
              "Name": "utc",
              "Type": "System.DateTime",
              "IsOptional": false,
              "DefaultValue": null,
              "IsOut": false,
              "IsRef": false,
              "Attributes": []
            }
          ],
          "Attributes": []
        },
        {
          "Name": ".ctor",
          "ReturnType": "System.Void",
          "IsStatic": false,
          "IsPublic": true,
          "IsVirtual": false,
          "IsAbstract": false,
          "IsConstructor": true,
          "Parameters": [],
          "Attributes": []
        }
      ],
      "Properties": [],
      "Events": [],
      "Attributes": []
    }
  ],
  "Interfaces": [],
  "Structs": [
    {
      "Name": "SYSTEMTIME",
      "Namespace": "",
      "FullName": "Ingr.SP2D.igrTimeConvert412.TimeConvert/SYSTEMTIME",
      "DeclaringType": "Ingr.SP2D.igrTimeConvert412.TimeConvert",
      "Properties": []
    },
    {
      "Name": "TIME_ZONE_INFORMATION",
      "Namespace": "",
      "FullName": "Ingr.SP2D.igrTimeConvert412.TimeConvert/TIME_ZONE_INFORMATION",
      "DeclaringType": "Ingr.SP2D.igrTimeConvert412.TimeConvert",
      "Properties": []
    }
  ],
  "Enums": [
    {
      "Name": "TimeZoneReturn",
      "Namespace": "",
      "FullName": "Ingr.SP2D.igrTimeConvert412.TimeConvert/TimeZoneReturn",
      "DeclaringType": "Ingr.SP2D.igrTimeConvert412.TimeConvert",
      "Values": [
        "TimeZoneCode",
        "TimeZoneName",
        "UTC_BaseOffset",
        "UTC_Offset",
        "DST_Active",
        "DST_Offset"
      ]
    }
  ],
  "Delegates": []
}