{
  "Id": "2543a9f3-6a5a-4c3a-ae14-e6f65b333c76",
  "DllName": "Microsoft.Practices.Prism.UnityExtensions",
  "Version": "4.1.0.0",
  "FilePath": "D:\\Off-Share\\P\u0026ID Workstation\\bin\\microsoft.practices.prism.unityextensions.dll",
  "Metadata": {
    "AssemblyName": "Microsoft.Practices.Prism.UnityExtensions",
    "Culture": null,
    "PublicKeyToken": null,
    "RuntimeVersion": "v4.0.30319",
    "ScanDate": "2026-06-07T12:43:41.6876614Z"
  },
  "Dependencies": [
    {
      "AssemblyName": "mscorlib",
      "Version": "4.0.0.0",
      "IsLocalDll": false,
      "ReferencedJsonFile": null
    },
    {
      "AssemblyName": "Microsoft.Practices.Prism",
      "Version": "4.1.0.0",
      "IsLocalDll": false,
      "ReferencedJsonFile": null
    },
    {
      "AssemblyName": "Microsoft.Practices.Unity",
      "Version": "2.1.505.0",
      "IsLocalDll": false,
      "ReferencedJsonFile": null
    },
    {
      "AssemblyName": "Microsoft.Practices.ServiceLocation",
      "Version": "1.0.0.0",
      "IsLocalDll": false,
      "ReferencedJsonFile": null
    },
    {
      "AssemblyName": "System.Core",
      "Version": "4.0.0.0",
      "IsLocalDll": false,
      "ReferencedJsonFile": null
    },
    {
      "AssemblyName": "System",
      "Version": "4.0.0.0",
      "IsLocalDll": false,
      "ReferencedJsonFile": null
    },
    {
      "AssemblyName": "WindowsBase",
      "Version": "4.0.0.0",
      "IsLocalDll": false,
      "ReferencedJsonFile": null
    },
    {
      "AssemblyName": "mscorlib",
      "Version": "2.0.0.0",
      "IsLocalDll": false,
      "ReferencedJsonFile": null
    }
  ],
  "Classes": [
    {
      "Name": "Resources",
      "Namespace": "Microsoft.Practices.Prism.UnityExtensions.Properties",
      "FullName": "Microsoft.Practices.Prism.UnityExtensions.Properties.Resources",
      "BaseType": "System.Object",
      "IsAbstract": false,
      "IsSealed": false,
      "DeclaringType": null,
      "ImplementedInterfaces": [],
      "Fields": [
        {
          "Name": "resourceMan",
          "Type": "System.Resources.ResourceManager",
          "IsPublic": false,
          "IsStatic": true,
          "IsReadonly": false,
          "Attributes": []
        },
        {
          "Name": "resourceCulture",
          "Type": "System.Globalization.CultureInfo",
          "IsPublic": false,
          "IsStatic": true,
          "IsReadonly": false,
          "Attributes": []
        }
      ],
      "Methods": [
        {
          "Name": ".ctor",
          "ReturnType": "System.Void",
          "IsStatic": false,
          "IsPublic": false,
          "IsVirtual": false,
          "IsAbstract": false,
          "IsConstructor": true,
          "Parameters": [],
          "Attributes": []
        }
      ],
      "Properties": [
        {
          "Name": "ResourceManager",
          "Type": "System.Resources.ResourceManager",
          "CanRead": true,
          "CanWrite": false
        },
        {
          "Name": "Culture",
          "Type": "System.Globalization.CultureInfo",
          "CanRead": true,
          "CanWrite": true
        },
        {
          "Name": "AddingUnityBootstrapperExtensionToContainer",
          "Type": "System.String",
          "CanRead": true,
          "CanWrite": false
        },
        {
          "Name": "BootstrapperSequenceCompleted",
          "Type": "System.String",
          "CanRead": true,
          "CanWrite": false
        },
        {
          "Name": "ConfiguringDefaultRegionBehaviors",
          "Type": "System.String",
          "CanRead": true,
          "CanWrite": false
        },
        {
          "Name": "ConfiguringModuleCatalog",
          "Type": "System.String",
          "CanRead": true,
          "CanWrite": false
        },
        {
          "Name": "ConfiguringRegionAdapters",
          "Type": "System.String",
          "CanRead": true,
          "CanWrite": false
        },
        {
          "Name": "ConfiguringServiceLocatorSingleton",
          "Type": "System.String",
          "CanRead": true,
          "CanWrite": false
        },
        {
          "Name": "ConfiguringUnityContainer",
          "Type": "System.String",
          "CanRead": true,
          "CanWrite": false
        },
        {
          "Name": "CreatingModuleCatalog",
          "Type": "System.String",
          "CanRead": true,
          "CanWrite": false
        },
        {
          "Name": "CreatingShell",
          "Type": "System.String",
          "CanRead": true,
          "CanWrite": false
        },
        {
          "Name": "CreatingUnityContainer",
          "Type": "System.String",
          "CanRead": true,
          "CanWrite": false
        },
        {
          "Name": "InitializingModules",
          "Type": "System.String",
          "CanRead": true,
          "CanWrite": false
        },
        {
          "Name": "InitializingShell",
          "Type": "System.String",
          "CanRead": true,
          "CanWrite": false
        },
        {
          "Name": "LoggerCreatedSuccessfully",
          "Type": "System.String",
          "CanRead": true,
          "CanWrite": false
        },
        {
          "Name": "NotOverwrittenGetModuleEnumeratorException",
          "Type": "System.String",
          "CanRead": true,
          "CanWrite": false
        },
        {
          "Name": "NullLoggerFacadeException",
          "Type": "System.String",
          "CanRead": true,
          "CanWrite": false
        },
        {
          "Name": "NullModuleCatalogException",
          "Type": "System.String",
          "CanRead": true,
          "CanWrite": false
        },
        {
          "Name": "NullUnityContainerException",
          "Type": "System.String",
          "CanRead": true,
          "CanWrite": false
        },
        {
          "Name": "RegisteringFrameworkExceptionTypes",
          "Type": "System.String",
          "CanRead": true,
          "CanWrite": false
        },
        {
          "Name": "SettingTheRegionManager",
          "Type": "System.String",
          "CanRead": true,
          "CanWrite": false
        },
        {
          "Name": "TypeMappingAlreadyRegistered",
          "Type": "System.String",
          "CanRead": true,
          "CanWrite": false
        },
        {
          "Name": "UpdatingRegions",
          "Type": "System.String",
          "CanRead": true,
          "CanWrite": false
        }
      ],
      "Events": [],
      "Attributes": []
    },
    {
      "Name": "UnityBootstrapper",
      "Namespace": "Microsoft.Practices.Prism.UnityExtensions",
      "FullName": "Microsoft.Practices.Prism.UnityExtensions.UnityBootstrapper",
      "BaseType": "Microsoft.Practices.Prism.Bootstrapper",
      "IsAbstract": true,
      "IsSealed": false,
      "DeclaringType": null,
      "ImplementedInterfaces": [],
      "Fields": [
        {
          "Name": "useDefaultConfiguration",
          "Type": "System.Boolean",
          "IsPublic": false,
          "IsStatic": false,
          "IsReadonly": false,
          "Attributes": []
        },
        {
          "Name": "\u003CContainer\u003Ek__BackingField",
          "Type": "Microsoft.Practices.Unity.IUnityContainer",
          "IsPublic": false,
          "IsStatic": false,
          "IsReadonly": false,
          "Attributes": []
        }
      ],
      "Methods": [
        {
          "Name": "Run",
          "ReturnType": "System.Void",
          "IsStatic": false,
          "IsPublic": true,
          "IsVirtual": true,
          "IsAbstract": false,
          "IsConstructor": false,
          "Parameters": [
            {
              "Name": "runWithDefaultConfiguration",
              "Type": "System.Boolean",
              "IsOptional": false,
              "DefaultValue": null,
              "IsOut": false,
              "IsRef": false,
              "Attributes": []
            }
          ],
          "Attributes": []
        },
        {
          "Name": "ConfigureServiceLocator",
          "ReturnType": "System.Void",
          "IsStatic": false,
          "IsPublic": false,
          "IsVirtual": true,
          "IsAbstract": false,
          "IsConstructor": false,
          "Parameters": [],
          "Attributes": []
        },
        {
          "Name": "RegisterFrameworkExceptionTypes",
          "ReturnType": "System.Void",
          "IsStatic": false,
          "IsPublic": false,
          "IsVirtual": true,
          "IsAbstract": false,
          "IsConstructor": false,
          "Parameters": [],
          "Attributes": []
        },
        {
          "Name": "ConfigureContainer",
          "ReturnType": "System.Void",
          "IsStatic": false,
          "IsPublic": false,
          "IsVirtual": true,
          "IsAbstract": false,
          "IsConstructor": false,
          "Parameters": [],
          "Attributes": []
        },
        {
          "Name": "InitializeModules",
          "ReturnType": "System.Void",
          "IsStatic": false,
          "IsPublic": false,
          "IsVirtual": true,
          "IsAbstract": false,
          "IsConstructor": false,
          "Parameters": [],
          "Attributes": []
        },
        {
          "Name": "CreateContainer",
          "ReturnType": "Microsoft.Practices.Unity.IUnityContainer",
          "IsStatic": false,
          "IsPublic": false,
          "IsVirtual": true,
          "IsAbstract": false,
          "IsConstructor": false,
          "Parameters": [],
          "Attributes": []
        },
        {
          "Name": "RegisterTypeIfMissing",
          "ReturnType": "System.Void",
          "IsStatic": false,
          "IsPublic": false,
          "IsVirtual": false,
          "IsAbstract": false,
          "IsConstructor": false,
          "Parameters": [
            {
              "Name": "fromType",
              "Type": "System.Type",
              "IsOptional": false,
              "DefaultValue": null,
              "IsOut": false,
              "IsRef": false,
              "Attributes": []
            },
            {
              "Name": "toType",
              "Type": "System.Type",
              "IsOptional": false,
              "DefaultValue": null,
              "IsOut": false,
              "IsRef": false,
              "Attributes": []
            },
            {
              "Name": "registerAsSingleton",
              "Type": "System.Boolean",
              "IsOptional": false,
              "DefaultValue": null,
              "IsOut": false,
              "IsRef": false,
              "Attributes": []
            }
          ],
          "Attributes": []
        },
        {
          "Name": ".ctor",
          "ReturnType": "System.Void",
          "IsStatic": false,
          "IsPublic": false,
          "IsVirtual": false,
          "IsAbstract": false,
          "IsConstructor": true,
          "Parameters": [],
          "Attributes": []
        },
        {
          "Name": "\u003CConfigureServiceLocator\u003Eb__0",
          "ReturnType": "Microsoft.Practices.ServiceLocation.IServiceLocator",
          "IsStatic": false,
          "IsPublic": false,
          "IsVirtual": false,
          "IsAbstract": false,
          "IsConstructor": false,
          "Parameters": [],
          "Attributes": []
        }
      ],
      "Properties": [
        {
          "Name": "Container",
          "Type": "Microsoft.Practices.Unity.IUnityContainer",
          "CanRead": true,
          "CanWrite": true
        }
      ],
      "Events": [],
      "Attributes": []
    },
    {
      "Name": "UnityBootstrapperExtension",
      "Namespace": "Microsoft.Practices.Prism.UnityExtensions",
      "FullName": "Microsoft.Practices.Prism.UnityExtensions.UnityBootstrapperExtension",
      "BaseType": "Microsoft.Practices.Unity.UnityContainerExtension",
      "IsAbstract": false,
      "IsSealed": false,
      "DeclaringType": null,
      "ImplementedInterfaces": [],
      "Fields": [],
      "Methods": [
        {
          "Name": "IsTypeRegistered",
          "ReturnType": "System.Boolean",
          "IsStatic": true,
          "IsPublic": true,
          "IsVirtual": false,
          "IsAbstract": false,
          "IsConstructor": false,
          "Parameters": [
            {
              "Name": "container",
              "Type": "Microsoft.Practices.Unity.IUnityContainer",
              "IsOptional": false,
              "DefaultValue": null,
              "IsOut": false,
              "IsRef": false,
              "Attributes": []
            },
            {
              "Name": "type",
              "Type": "System.Type",
              "IsOptional": false,
              "DefaultValue": null,
              "IsOut": false,
              "IsRef": false,
              "Attributes": []
            }
          ],
          "Attributes": []
        },
        {
          "Name": "Initialize",
          "ReturnType": "System.Void",
          "IsStatic": false,
          "IsPublic": false,
          "IsVirtual": true,
          "IsAbstract": false,
          "IsConstructor": false,
          "Parameters": [],
          "Attributes": []
        },
        {
          "Name": ".ctor",
          "ReturnType": "System.Void",
          "IsStatic": false,
          "IsPublic": true,
          "IsVirtual": false,
          "IsAbstract": false,
          "IsConstructor": true,
          "Parameters": [],
          "Attributes": []
        }
      ],
      "Properties": [],
      "Events": [],
      "Attributes": []
    },
    {
      "Name": "UnityServiceLocatorAdapter",
      "Namespace": "Microsoft.Practices.Prism.UnityExtensions",
      "FullName": "Microsoft.Practices.Prism.UnityExtensions.UnityServiceLocatorAdapter",
      "BaseType": "Microsoft.Practices.ServiceLocation.ServiceLocatorImplBase",
      "IsAbstract": false,
      "IsSealed": false,
      "DeclaringType": null,
      "ImplementedInterfaces": [],
      "Fields": [
        {
          "Name": "_unityContainer",
          "Type": "Microsoft.Practices.Unity.IUnityContainer",
          "IsPublic": false,
          "IsStatic": false,
          "IsReadonly": true,
          "Attributes": []
        }
      ],
      "Methods": [
        {
          "Name": ".ctor",
          "ReturnType": "System.Void",
          "IsStatic": false,
          "IsPublic": true,
          "IsVirtual": false,
          "IsAbstract": false,
          "IsConstructor": true,
          "Parameters": [
            {
              "Name": "unityContainer",
              "Type": "Microsoft.Practices.Unity.IUnityContainer",
              "IsOptional": false,
              "DefaultValue": null,
              "IsOut": false,
              "IsRef": false,
              "Attributes": []
            }
          ],
          "Attributes": []
        },
        {
          "Name": "DoGetInstance",
          "ReturnType": "System.Object",
          "IsStatic": false,
          "IsPublic": false,
          "IsVirtual": true,
          "IsAbstract": false,
          "IsConstructor": false,
          "Parameters": [
            {
              "Name": "serviceType",
              "Type": "System.Type",
              "IsOptional": false,
              "DefaultValue": null,
              "IsOut": false,
              "IsRef": false,
              "Attributes": []
            },
            {
              "Name": "key",
              "Type": "System.String",
              "IsOptional": false,
              "DefaultValue": null,
              "IsOut": false,
              "IsRef": false,
              "Attributes": []
            }
          ],
          "Attributes": []
        },
        {
          "Name": "DoGetAllInstances",
          "ReturnType": "System.Collections.Generic.IEnumerable\u00601\u003CSystem.Object\u003E",
          "IsStatic": false,
          "IsPublic": false,
          "IsVirtual": true,
          "IsAbstract": false,
          "IsConstructor": false,
          "Parameters": [
            {
              "Name": "serviceType",
              "Type": "System.Type",
              "IsOptional": false,
              "DefaultValue": null,
              "IsOut": false,
              "IsRef": false,
              "Attributes": []
            }
          ],
          "Attributes": []
        }
      ],
      "Properties": [],
      "Events": [],
      "Attributes": []
    },
    {
      "Name": "UnityContainerHelper",
      "Namespace": "Microsoft.Practices.Prism.UnityExtensions",
      "FullName": "Microsoft.Practices.Prism.UnityExtensions.UnityContainerHelper",
      "BaseType": "System.Object",
      "IsAbstract": true,
      "IsSealed": true,
      "DeclaringType": null,
      "ImplementedInterfaces": [],
      "Fields": [],
      "Methods": [
        {
          "Name": "IsTypeRegistered",
          "ReturnType": "System.Boolean",
          "IsStatic": true,
          "IsPublic": true,
          "IsVirtual": false,
          "IsAbstract": false,
          "IsConstructor": false,
          "Parameters": [
            {
              "Name": "container",
              "Type": "Microsoft.Practices.Unity.IUnityContainer",
              "IsOptional": false,
              "DefaultValue": null,
              "IsOut": false,
              "IsRef": false,
              "Attributes": []
            },
            {
              "Name": "type",
              "Type": "System.Type",
              "IsOptional": false,
              "DefaultValue": null,
              "IsOut": false,
              "IsRef": false,
              "Attributes": []
            }
          ],
          "Attributes": []
        },
        {
          "Name": "TryResolve",
          "ReturnType": "T",
          "IsStatic": true,
          "IsPublic": true,
          "IsVirtual": false,
          "IsAbstract": false,
          "IsConstructor": false,
          "Parameters": [
            {
              "Name": "container",
              "Type": "Microsoft.Practices.Unity.IUnityContainer",
              "IsOptional": false,
              "DefaultValue": null,
              "IsOut": false,
              "IsRef": false,
              "Attributes": []
            }
          ],
          "Attributes": []
        },
        {
          "Name": "TryResolve",
          "ReturnType": "System.Object",
          "IsStatic": true,
          "IsPublic": true,
          "IsVirtual": false,
          "IsAbstract": false,
          "IsConstructor": false,
          "Parameters": [
            {
              "Name": "container",
              "Type": "Microsoft.Practices.Unity.IUnityContainer",
              "IsOptional": false,
              "DefaultValue": null,
              "IsOut": false,
              "IsRef": false,
              "Attributes": []
            },
            {
              "Name": "typeToResolve",
              "Type": "System.Type",
              "IsOptional": false,
              "DefaultValue": null,
              "IsOut": false,
              "IsRef": false,
              "Attributes": []
            }
          ],
          "Attributes": []
        }
      ],
      "Properties": [],
      "Events": [],
      "Attributes": []
    }
  ],
  "Interfaces": [],
  "Structs": [],
  "Enums": [],
  "Delegates": []
}